{"path":"%D0%AD%D0%BD%D1%86%D0%B5%D0%BB%D0%B8%D1%8F%20%D1%88%D0%B5%D0%BB%D1%83%D1%88%D0%B8%D1%81%D1%82%D0%B0%D1%8F%20-%20Encoelia%20furfuracea","deepCounters":{"total":25,"images":25,"files":25},"counters":{"total":25,"images":25,"files":25},"thumb":{"path":"thumbs\/2024-03-16-07.02.46%20ZS%20PMax.webp","width":512,"height":410},"thumbCaption":"<h3> Encoelia furfuracea - Энцелия шелушистая - Spring Hazelcup - Hasel-Kleiebecherling<\/h3><div class=\"comment\">Encoelia furfuracea is a species of fungus known for its distinctive appearance and ecological role. It typically has small fruiting bodies with caps ranging&hellip;<\/div>","album":{"description":"Fungarium.INFO. Fungarium Photo Collection: Boletes, Toadstools, Agaricomycetes, Fungi, Molds and Myxomycetes.<br\/>\n<br\/><i><b>517<\/b> species in <b>40<\/b> orders and <b>112<\/b> families photographed.<br\/>\n<br\/><b>8503<\/b> images total.<\/i><br\/><br\/>\nTry also other sites: <br\/>\n    <a href=\"https:\/\/herbariuminfo.netlify.app\">Herbarium.INFO<\/a>&nbsp;\u2022&nbsp;\n    <a href=\"https:\/\/plantariuminfo.netlify.app\">Plantarium.INFO<\/a>&nbsp;\u2022&nbsp;\n    <a href=\"https:\/\/fungarium.netlify.app\">Fungarium.INFO<\/a>&nbsp;\u2022&nbsp;\n    <a href=\"https:\/\/lichenarium.netlify.app\">Lichenarium.INFO<\/a>&nbsp;\u2022&nbsp;\n    <a href=\"https:\/\/algaerium.netlify.app\">Algaerium.INFO<\/a>","title":"Fungarium.INFO Fungi: Photo and Catalog"},"objects":[{"path":"2024-03-16-07.02.46%20ZS%20PMax.webp","image":{"path":"slides\/2024-03-16-07.02.46%20ZS%20PMax.webp","width":2000,"height":1497},"imageCaption":"<div class=\"title\">2024-03-16-07.02.46 ZS PMax<\/div>","thumb":{"path":"thumbs\/2024-03-16-07.02.46%20ZS%20PMax.webp","width":512,"height":410},"fileSize":3092727,"thumbCaption":"<span class=\"nr\">1<\/span><div class=\"title\">2024-03-16-07.02.46 ZS PMax<\/div>","name":"2024-03-16-07.02.46 ZS PMax.webp","dates":{"added":1710623416,"dateTaken":1710622733},"fileDate":"2024-03-16T22:58:53.497Z","category":"image","camera":{"originalDate":"2024-03-16T22:58:53.497Z"}},{"path":"2024-03-16-08.34.54%20ZS%20PMax.webp","image":{"path":"slides\/2024-03-16-08.34.54%20ZS%20PMax.webp","width":2000,"height":1477},"imageCaption":"<div class=\"title\">2024-03-16-08.34.54 ZS PMax<\/div>","thumb":{"path":"thumbs\/2024-03-16-08.34.54%20ZS%20PMax.webp","width":512,"height":410},"fileSize":2474344,"thumbCaption":"<span class=\"nr\">2<\/span><div class=\"title\">2024-03-16-08.34.54 ZS PMax<\/div>","name":"2024-03-16-08.34.54 ZS PMax.webp","dates":{"added":1710623416,"dateTaken":1710622749},"fileDate":"2024-03-16T22:59:09.0Z","category":"image","camera":{"originalDate":"2024-03-16T22:59:09.0Z"}},{"path":"2024-03-16-08.56.28%20ZS%20PMax.webp","image":{"path":"slides\/2024-03-16-08.56.28%20ZS%20PMax.webp","width":2000,"height":1505},"imageCaption":"<div class=\"title\">2024-03-16-08.56.28 ZS PMax<\/div>","thumb":{"path":"thumbs\/2024-03-16-08.56.28%20ZS%20PMax.webp","width":512,"height":410},"fileSize":3110097,"thumbCaption":"<span class=\"nr\">3<\/span><div class=\"title\">2024-03-16-08.56.28 ZS PMax<\/div>","name":"2024-03-16-08.56.28 ZS PMax.webp","dates":{"added":1710623416,"dateTaken":1710622764},"fileDate":"2024-03-16T22:59:24.154Z","category":"image","camera":{"originalDate":"2024-03-16T22:59:24.154Z"}},{"image":{"path":"slides\/encoelia-furfuracea-1.webp","width":2000,"height":1333},"creator":"Boriss Melikjan","thumb":{"path":"thumbs\/encoelia-furfuracea-1.webp","width":512,"height":410},"thumbCaption":"<span class=\"nr\">4<\/span><div class=\"title\">encoelia-furfuracea-1<\/div>","photodata":"<b>Photographer<\/b> <i>Boriss Melikjan<\/i> &middot; <b>Original Date<\/b> <i>3\/16\/24, 2:43\u202FPM<\/i> &middot; <b>Make<\/b> <i>SONY<\/i> &middot; <b>Camera<\/b> <i>ILCE-7M3<\/i> &middot; <b>Lens Model<\/b> <i>FE 50mm F2.8 Macro<\/i> &middot; <b>Focal Length (35mm)<\/b> <i>50mm<\/i> &middot; <b>Metering Mode<\/b> <i>Multi-segment<\/i> &middot; <b>ISO Equivalent<\/b> <i>6400<\/i> &middot; <b>Exposure Time<\/b> <i>1\/200s<\/i> &middot; <b>Aperture<\/b> <i>ƒ\/16.0<\/i> &middot; <b>Exposure bias<\/b> <i>0 EV<\/i> &middot; <b>Exposure Program<\/b> <i>Manual control<\/i> &middot; <b>White balance<\/b> <i>Auto white balance<\/i> &middot; <b>Flash<\/b> <i>Flash did not fire<\/i>","dates":{"added":1710623416,"dateTaken":1710593007},"fileDate":"2024-03-16T22:28:14.937Z","path":"encoelia-furfuracea-1.webp","imageCaption":"<div class=\"title\">encoelia-furfuracea-1<\/div>","fileSize":14141683,"rights":"Fungarium.info","name":"encoelia-furfuracea-1.webp","category":"image","camera":{"aperture":16.0,"exposureTime":"1\/200s","originalDate":"2024-03-16T14:43:27.0Z","cameraModel":"ILCE-7M3","focalLength35mm":"50mm","cameraMake":"SONY","isoEquivalent":6400,"flash":"Flash did not fire","focalLength":"50mm"}},{"image":{"path":"slides\/encoelia-furfuracea-2.webp","width":2000,"height":1333},"creator":"Boriss Melikjan","thumb":{"path":"thumbs\/encoelia-furfuracea-2.webp","width":512,"height":410},"thumbCaption":"<span class=\"nr\">5<\/span><div class=\"title\">encoelia-furfuracea-2<\/div>","photodata":"<b>Photographer<\/b> <i>Boriss Melikjan<\/i> &middot; <b>Original Date<\/b> <i>3\/16\/24, 2:43\u202FPM<\/i> &middot; <b>Make<\/b> <i>SONY<\/i> &middot; <b>Camera<\/b> <i>ILCE-7M3<\/i> &middot; <b>Lens Model<\/b> <i>FE 50mm F2.8 Macro<\/i> &middot; <b>Focal Length (35mm)<\/b> <i>50mm<\/i> &middot; <b>Metering Mode<\/b> <i>Multi-segment<\/i> &middot; <b>ISO Equivalent<\/b> <i>6400<\/i> &middot; <b>Exposure Time<\/b> <i>1\/200s<\/i> &middot; <b>Aperture<\/b> <i>ƒ\/16.0<\/i> &middot; <b>Exposure bias<\/b> <i>0 EV<\/i> &middot; <b>Exposure Program<\/b> <i>Manual control<\/i> &middot; <b>White balance<\/b> <i>Auto white balance<\/i> &middot; <b>Flash<\/b> <i>Flash did not fire<\/i>","dates":{"added":1710623416,"dateTaken":1710593008},"fileDate":"2024-03-16T22:28:14.922Z","path":"encoelia-furfuracea-2.webp","imageCaption":"<div class=\"title\">encoelia-furfuracea-2<\/div>","fileSize":13974525,"rights":"Fungarium.info","name":"encoelia-furfuracea-2.webp","category":"image","camera":{"aperture":16.0,"exposureTime":"1\/200s","originalDate":"2024-03-16T14:43:28.0Z","cameraModel":"ILCE-7M3","focalLength35mm":"50mm","cameraMake":"SONY","isoEquivalent":6400,"flash":"Flash did not fire","focalLength":"50mm"}},{"image":{"path":"slides\/encoelia-furfuracea-4.webp","width":2000,"height":1333},"creator":"Boriss Melikjan","thumb":{"path":"thumbs\/encoelia-furfuracea-4.webp","width":512,"height":410},"thumbCaption":"<span class=\"nr\">6<\/span><div class=\"title\">encoelia-furfuracea-4<\/div>","photodata":"<b>Photographer<\/b> <i>Boriss Melikjan<\/i> &middot; <b>Original Date<\/b> <i>3\/16\/24, 2:44\u202FPM<\/i> &middot; <b>Make<\/b> <i>SONY<\/i> &middot; <b>Camera<\/b> <i>ILCE-7M3<\/i> &middot; <b>Lens Model<\/b> <i>FE 50mm F2.8 Macro<\/i> &middot; <b>Focal Length (35mm)<\/b> <i>50mm<\/i> &middot; <b>Metering Mode<\/b> <i>Multi-segment<\/i> &middot; <b>ISO Equivalent<\/b> <i>6400<\/i> &middot; <b>Exposure Time<\/b> <i>1\/200s<\/i> &middot; <b>Aperture<\/b> <i>ƒ\/16.0<\/i> &middot; <b>Exposure bias<\/b> <i>0 EV<\/i> &middot; <b>Exposure Program<\/b> <i>Manual control<\/i> &middot; <b>White balance<\/b> <i>Auto white balance<\/i> &middot; <b>Flash<\/b> <i>Flash did not fire<\/i>","dates":{"added":1710623416,"dateTaken":1710593050},"fileDate":"2024-03-16T22:28:15.15Z","path":"encoelia-furfuracea-4.webp","imageCaption":"<div class=\"title\">encoelia-furfuracea-4<\/div>","fileSize":14750587,"rights":"Fungarium.info","name":"encoelia-furfuracea-4.webp","category":"image","camera":{"aperture":16.0,"exposureTime":"1\/200s","originalDate":"2024-03-16T14:44:10.0Z","cameraModel":"ILCE-7M3","focalLength35mm":"50mm","cameraMake":"SONY","isoEquivalent":6400,"flash":"Flash did not fire","focalLength":"50mm"}},{"image":{"path":"slides\/encoelia-furfuracea-5.webp","width":2000,"height":1333},"creator":"Boriss Melikjan","thumb":{"path":"thumbs\/encoelia-furfuracea-5.webp","width":512,"height":410},"thumbCaption":"<span class=\"nr\">7<\/span><div class=\"title\">encoelia-furfuracea-5<\/div>","photodata":"<b>Photographer<\/b> <i>Boriss Melikjan<\/i> &middot; <b>Original Date<\/b> <i>3\/16\/24, 2:44\u202FPM<\/i> &middot; <b>Make<\/b> <i>SONY<\/i> &middot; <b>Camera<\/b> <i>ILCE-7M3<\/i> &middot; <b>Lens Model<\/b> <i>FE 50mm F2.8 Macro<\/i> &middot; <b>Focal Length (35mm)<\/b> <i>50mm<\/i> &middot; <b>Metering Mode<\/b> <i>Multi-segment<\/i> &middot; <b>ISO Equivalent<\/b> <i>6400<\/i> &middot; <b>Exposure Time<\/b> <i>1\/200s<\/i> &middot; <b>Aperture<\/b> <i>ƒ\/16.0<\/i> &middot; <b>Exposure bias<\/b> <i>0 EV<\/i> &middot; <b>Exposure Program<\/b> <i>Manual control<\/i> &middot; <b>White balance<\/b> <i>Auto white balance<\/i> &middot; <b>Flash<\/b> <i>Flash did not fire<\/i>","dates":{"added":1710623416,"dateTaken":1710593050},"fileDate":"2024-03-16T22:28:15.260Z","path":"encoelia-furfuracea-5.webp","imageCaption":"<div class=\"title\">encoelia-furfuracea-5<\/div>","fileSize":14009775,"rights":"Fungarium.info","name":"encoelia-furfuracea-5.webp","category":"image","camera":{"aperture":16.0,"exposureTime":"1\/200s","originalDate":"2024-03-16T14:44:10.0Z","cameraModel":"ILCE-7M3","focalLength35mm":"50mm","cameraMake":"SONY","isoEquivalent":6400,"flash":"Flash did not fire","focalLength":"50mm"}},{"image":{"path":"slides\/encoelia-furfuracea-6.webp","width":2000,"height":1333},"creator":"Boriss Melikjan","thumb":{"path":"thumbs\/encoelia-furfuracea-6.webp","width":512,"height":410},"thumbCaption":"<span class=\"nr\">8<\/span><div class=\"title\">encoelia-furfuracea-6<\/div>","photodata":"<b>Photographer<\/b> <i>Boriss Melikjan<\/i> &middot; <b>Original Date<\/b> <i>3\/16\/24, 2:44\u202FPM<\/i> &middot; <b>Make<\/b> <i>SONY<\/i> &middot; <b>Camera<\/b> <i>ILCE-7M3<\/i> &middot; <b>Lens Model<\/b> <i>FE 50mm F2.8 Macro<\/i> &middot; <b>Focal Length (35mm)<\/b> <i>50mm<\/i> &middot; <b>Metering Mode<\/b> <i>Multi-segment<\/i> &middot; <b>ISO Equivalent<\/b> <i>6400<\/i> &middot; <b>Exposure Time<\/b> <i>1\/200s<\/i> &middot; <b>Aperture<\/b> <i>ƒ\/16.0<\/i> &middot; <b>Exposure bias<\/b> <i>0 EV<\/i> &middot; <b>Exposure Program<\/b> <i>Manual control<\/i> &middot; <b>White balance<\/b> <i>Auto white balance<\/i> &middot; <b>Flash<\/b> <i>Flash did not fire<\/i>","dates":{"added":1710623416,"dateTaken":1710593061},"fileDate":"2024-03-16T22:28:15.73Z","path":"encoelia-furfuracea-6.webp","imageCaption":"<div class=\"title\">encoelia-furfuracea-6<\/div>","fileSize":14423367,"rights":"Fungarium.info","name":"encoelia-furfuracea-6.webp","category":"image","camera":{"aperture":16.0,"exposureTime":"1\/200s","originalDate":"2024-03-16T14:44:21.0Z","cameraModel":"ILCE-7M3","focalLength35mm":"50mm","cameraMake":"SONY","isoEquivalent":6400,"flash":"Flash did not fire","focalLength":"50mm"}},{"image":{"path":"slides\/encoelia-furfuracea-7.webp","width":2000,"height":1333},"creator":"Boriss Melikjan","thumb":{"path":"thumbs\/encoelia-furfuracea-7.webp","width":512,"height":410},"thumbCaption":"<span class=\"nr\">9<\/span><div class=\"title\">encoelia-furfuracea-7<\/div>","photodata":"<b>Photographer<\/b> <i>Boriss Melikjan<\/i> &middot; <b>Original Date<\/b> <i>3\/16\/24, 2:44\u202FPM<\/i> &middot; <b>Make<\/b> <i>SONY<\/i> &middot; <b>Camera<\/b> <i>ILCE-7M3<\/i> &middot; <b>Lens Model<\/b> <i>FE 50mm F2.8 Macro<\/i> &middot; <b>Focal Length (35mm)<\/b> <i>50mm<\/i> &middot; <b>Metering Mode<\/b> <i>Multi-segment<\/i> &middot; <b>ISO Equivalent<\/b> <i>6400<\/i> &middot; <b>Exposure Time<\/b> <i>1\/200s<\/i> &middot; <b>Aperture<\/b> <i>ƒ\/16.0<\/i> &middot; <b>Exposure bias<\/b> <i>0 EV<\/i> &middot; <b>Exposure Program<\/b> <i>Manual control<\/i> &middot; <b>White balance<\/b> <i>Auto white balance<\/i> &middot; <b>Flash<\/b> <i>Flash did not fire<\/i>","dates":{"added":1710623416,"dateTaken":1710593061},"fileDate":"2024-03-16T22:28:15.812Z","path":"encoelia-furfuracea-7.webp","imageCaption":"<div class=\"title\">encoelia-furfuracea-7<\/div>","fileSize":14429228,"rights":"Fungarium.info","name":"encoelia-furfuracea-7.webp","category":"image","camera":{"aperture":16.0,"exposureTime":"1\/200s","originalDate":"2024-03-16T14:44:21.0Z","cameraModel":"ILCE-7M3","focalLength35mm":"50mm","cameraMake":"SONY","isoEquivalent":6400,"flash":"Flash did not fire","focalLength":"50mm"}},{"image":{"path":"slides\/encoelia-furfuracea-9.webp","width":2000,"height":1333},"creator":"Boriss Melikjan","thumb":{"path":"thumbs\/encoelia-furfuracea-9.webp","width":512,"height":410},"thumbCaption":"<span class=\"nr\">10<\/span><div class=\"title\">encoelia-furfuracea-9<\/div>","photodata":"<b>Photographer<\/b> <i>Boriss Melikjan<\/i> &middot; <b>Original Date<\/b> <i>3\/16\/24, 2:44\u202FPM<\/i> &middot; <b>Make<\/b> <i>SONY<\/i> &middot; <b>Camera<\/b> <i>ILCE-7M3<\/i> &middot; <b>Lens Model<\/b> <i>FE 50mm F2.8 Macro<\/i> &middot; <b>Focal Length (35mm)<\/b> <i>50mm<\/i> &middot; <b>Metering Mode<\/b> <i>Multi-segment<\/i> &middot; <b>ISO Equivalent<\/b> <i>6400<\/i> &middot; <b>Exposure Time<\/b> <i>1\/200s<\/i> &middot; <b>Aperture<\/b> <i>ƒ\/16.0<\/i> &middot; <b>Exposure bias<\/b> <i>0 EV<\/i> &middot; <b>Exposure Program<\/b> <i>Manual control<\/i> &middot; <b>White balance<\/b> <i>Auto white balance<\/i> &middot; <b>Flash<\/b> <i>Flash did not fire<\/i>","dates":{"added":1710623416,"dateTaken":1710593078},"fileDate":"2024-03-16T22:28:15.884Z","path":"encoelia-furfuracea-9.webp","imageCaption":"<div class=\"title\">encoelia-furfuracea-9<\/div>","fileSize":14690447,"rights":"Fungarium.info","name":"encoelia-furfuracea-9.webp","category":"image","camera":{"aperture":16.0,"exposureTime":"1\/200s","originalDate":"2024-03-16T14:44:38.0Z","cameraModel":"ILCE-7M3","focalLength35mm":"50mm","cameraMake":"SONY","isoEquivalent":6400,"flash":"Flash did not fire","focalLength":"50mm"}},{"image":{"path":"slides\/encoelia-furfuracea-10.webp","width":2000,"height":1333},"creator":"Boriss Melikjan","thumb":{"path":"thumbs\/encoelia-furfuracea-10.webp","width":512,"height":410},"thumbCaption":"<span class=\"nr\">11<\/span><div class=\"title\">encoelia-furfuracea-10<\/div>","photodata":"<b>Photographer<\/b> <i>Boriss Melikjan<\/i> &middot; <b>Original Date<\/b> <i>3\/16\/24, 2:44\u202FPM<\/i> &middot; <b>Make<\/b> <i>SONY<\/i> &middot; <b>Camera<\/b> <i>ILCE-7M3<\/i> &middot; <b>Lens Model<\/b> <i>FE 50mm F2.8 Macro<\/i> &middot; <b>Focal Length (35mm)<\/b> <i>50mm<\/i> &middot; <b>Metering Mode<\/b> <i>Multi-segment<\/i> &middot; <b>ISO Equivalent<\/b> <i>6400<\/i> &middot; <b>Exposure Time<\/b> <i>1\/200s<\/i> &middot; <b>Aperture<\/b> <i>ƒ\/16.0<\/i> &middot; <b>Exposure bias<\/b> <i>0 EV<\/i> &middot; <b>Exposure Program<\/b> <i>Manual control<\/i> &middot; <b>White balance<\/b> <i>Auto white balance<\/i> &middot; <b>Flash<\/b> <i>Flash did not fire<\/i>","dates":{"added":1710623416,"dateTaken":1710593083},"fileDate":"2024-03-16T22:28:21.399Z","path":"encoelia-furfuracea-10.webp","imageCaption":"<div class=\"title\">encoelia-furfuracea-10<\/div>","fileSize":12771731,"rights":"Fungarium.info","name":"encoelia-furfuracea-10.webp","category":"image","camera":{"aperture":16.0,"exposureTime":"1\/200s","originalDate":"2024-03-16T14:44:43.0Z","cameraModel":"ILCE-7M3","focalLength35mm":"50mm","cameraMake":"SONY","isoEquivalent":6400,"flash":"Flash did not fire","focalLength":"50mm"}},{"image":{"path":"slides\/encoelia-furfuracea-11.webp","width":2000,"height":1333},"creator":"Boriss Melikjan","thumb":{"path":"thumbs\/encoelia-furfuracea-11.webp","width":512,"height":410},"thumbCaption":"<span class=\"nr\">12<\/span><div class=\"title\">encoelia-furfuracea-11<\/div>","photodata":"<b>Photographer<\/b> <i>Boriss Melikjan<\/i> &middot; <b>Original Date<\/b> <i>3\/16\/24, 2:44\u202FPM<\/i> &middot; <b>Make<\/b> <i>SONY<\/i> &middot; <b>Camera<\/b> <i>ILCE-7M3<\/i> &middot; <b>Lens Model<\/b> <i>FE 50mm F2.8 Macro<\/i> &middot; <b>Focal Length (35mm)<\/b> <i>50mm<\/i> &middot; <b>Metering Mode<\/b> <i>Multi-segment<\/i> &middot; <b>ISO Equivalent<\/b> <i>6400<\/i> &middot; <b>Exposure Time<\/b> <i>1\/200s<\/i> &middot; <b>Aperture<\/b> <i>ƒ\/16.0<\/i> &middot; <b>Exposure bias<\/b> <i>0 EV<\/i> &middot; <b>Exposure Program<\/b> <i>Manual control<\/i> &middot; <b>White balance<\/b> <i>Auto white balance<\/i> &middot; <b>Flash<\/b> <i>Flash did not fire<\/i>","dates":{"added":1710623416,"dateTaken":1710593083},"fileDate":"2024-03-16T22:28:21.476Z","path":"encoelia-furfuracea-11.webp","imageCaption":"<div class=\"title\">encoelia-furfuracea-11<\/div>","fileSize":12896459,"rights":"Fungarium.info","name":"encoelia-furfuracea-11.webp","category":"image","camera":{"aperture":16.0,"exposureTime":"1\/200s","originalDate":"2024-03-16T14:44:43.0Z","cameraModel":"ILCE-7M3","focalLength35mm":"50mm","cameraMake":"SONY","isoEquivalent":6400,"flash":"Flash did not fire","focalLength":"50mm"}},{"image":{"path":"slides\/encoelia-furfuracea-12.webp","width":2000,"height":1333},"creator":"Boriss Melikjan","thumb":{"path":"thumbs\/encoelia-furfuracea-12.webp","width":512,"height":410},"thumbCaption":"<span class=\"nr\">13<\/span><div class=\"title\">encoelia-furfuracea-12<\/div>","photodata":"<b>Photographer<\/b> <i>Boriss Melikjan<\/i> &middot; <b>Original Date<\/b> <i>3\/16\/24, 2:44\u202FPM<\/i> &middot; <b>Make<\/b> <i>SONY<\/i> &middot; <b>Camera<\/b> <i>ILCE-7M3<\/i> &middot; <b>Lens Model<\/b> <i>FE 50mm F2.8 Macro<\/i> &middot; <b>Focal Length (35mm)<\/b> <i>50mm<\/i> &middot; <b>Metering Mode<\/b> <i>Multi-segment<\/i> &middot; <b>ISO Equivalent<\/b> <i>6400<\/i> &middot; <b>Exposure Time<\/b> <i>1\/200s<\/i> &middot; <b>Aperture<\/b> <i>ƒ\/16.0<\/i> &middot; <b>Exposure bias<\/b> <i>0 EV<\/i> &middot; <b>Exposure Program<\/b> <i>Manual control<\/i> &middot; <b>White balance<\/b> <i>Auto white balance<\/i> &middot; <b>Flash<\/b> <i>Flash did not fire<\/i>","dates":{"added":1710623416,"dateTaken":1710593084},"fileDate":"2024-03-16T22:28:21.414Z","path":"encoelia-furfuracea-12.webp","imageCaption":"<div class=\"title\">encoelia-furfuracea-12<\/div>","fileSize":13105990,"rights":"Fungarium.info","name":"encoelia-furfuracea-12.webp","category":"image","camera":{"aperture":16.0,"exposureTime":"1\/200s","originalDate":"2024-03-16T14:44:44.0Z","cameraModel":"ILCE-7M3","focalLength35mm":"50mm","cameraMake":"SONY","isoEquivalent":6400,"flash":"Flash did not fire","focalLength":"50mm"}},{"image":{"path":"slides\/encoelia-furfuracea-13.webp","width":2000,"height":1333},"creator":"Boriss Melikjan","thumb":{"path":"thumbs\/encoelia-furfuracea-13.webp","width":512,"height":410},"thumbCaption":"<span class=\"nr\">14<\/span><div class=\"title\">encoelia-furfuracea-13<\/div>","photodata":"<b>Photographer<\/b> <i>Boriss Melikjan<\/i> &middot; <b>Original Date<\/b> <i>3\/16\/24, 2:44\u202FPM<\/i> &middot; <b>Make<\/b> <i>SONY<\/i> &middot; <b>Camera<\/b> <i>ILCE-7M3<\/i> &middot; <b>Lens Model<\/b> <i>FE 50mm F2.8 Macro<\/i> &middot; <b>Focal Length (35mm)<\/b> <i>50mm<\/i> &middot; <b>Metering Mode<\/b> <i>Multi-segment<\/i> &middot; <b>ISO Equivalent<\/b> <i>6400<\/i> &middot; <b>Exposure Time<\/b> <i>1\/200s<\/i> &middot; <b>Aperture<\/b> <i>ƒ\/16.0<\/i> &middot; <b>Exposure bias<\/b> <i>0 EV<\/i> &middot; <b>Exposure Program<\/b> <i>Manual control<\/i> &middot; <b>White balance<\/b> <i>Auto white balance<\/i> &middot; <b>Flash<\/b> <i>Flash did not fire<\/i>","dates":{"added":1710623416,"dateTaken":1710593088},"fileDate":"2024-03-16T22:28:21.608Z","path":"encoelia-furfuracea-13.webp","imageCaption":"<div class=\"title\">encoelia-furfuracea-13<\/div>","fileSize":13541938,"rights":"Fungarium.info","name":"encoelia-furfuracea-13.webp","category":"image","camera":{"aperture":16.0,"exposureTime":"1\/200s","originalDate":"2024-03-16T14:44:48.0Z","cameraModel":"ILCE-7M3","focalLength35mm":"50mm","cameraMake":"SONY","isoEquivalent":6400,"flash":"Flash did not fire","focalLength":"50mm"}},{"image":{"path":"slides\/encoelia-furfuracea-14.webp","width":2000,"height":1333},"creator":"Boriss Melikjan","thumb":{"path":"thumbs\/encoelia-furfuracea-14.webp","width":512,"height":410},"thumbCaption":"<span class=\"nr\">15<\/span><div class=\"title\">encoelia-furfuracea-14<\/div>","photodata":"<b>Photographer<\/b> <i>Boriss Melikjan<\/i> &middot; <b>Original Date<\/b> <i>3\/16\/24, 2:44\u202FPM<\/i> &middot; <b>Make<\/b> <i>SONY<\/i> &middot; <b>Camera<\/b> <i>ILCE-7M3<\/i> &middot; <b>Lens Model<\/b> <i>FE 50mm F2.8 Macro<\/i> &middot; <b>Focal Length (35mm)<\/b> <i>50mm<\/i> &middot; <b>Metering Mode<\/b> <i>Multi-segment<\/i> &middot; <b>ISO Equivalent<\/b> <i>6400<\/i> &middot; <b>Exposure Time<\/b> <i>1\/200s<\/i> &middot; <b>Aperture<\/b> <i>ƒ\/16.0<\/i> &middot; <b>Exposure bias<\/b> <i>0 EV<\/i> &middot; <b>Exposure Program<\/b> <i>Manual control<\/i> &middot; <b>White balance<\/b> <i>Auto white balance<\/i> &middot; <b>Flash<\/b> <i>Flash did not fire<\/i>","dates":{"added":1710623416,"dateTaken":1710593089},"fileDate":"2024-03-16T22:28:21.924Z","path":"encoelia-furfuracea-14.webp","imageCaption":"<div class=\"title\">encoelia-furfuracea-14<\/div>","fileSize":12920685,"rights":"Fungarium.info","name":"encoelia-furfuracea-14.webp","category":"image","camera":{"aperture":16.0,"exposureTime":"1\/200s","originalDate":"2024-03-16T14:44:49.0Z","cameraModel":"ILCE-7M3","focalLength35mm":"50mm","cameraMake":"SONY","isoEquivalent":6400,"flash":"Flash did not fire","focalLength":"50mm"}},{"image":{"path":"slides\/encoelia-furfuracea-15.webp","width":2000,"height":1333},"creator":"Boriss Melikjan","thumb":{"path":"thumbs\/encoelia-furfuracea-15.webp","width":512,"height":410},"thumbCaption":"<span class=\"nr\">16<\/span><div class=\"title\">encoelia-furfuracea-15<\/div>","photodata":"<b>Photographer<\/b> <i>Boriss Melikjan<\/i> &middot; <b>Original Date<\/b> <i>3\/16\/24, 2:44\u202FPM<\/i> &middot; <b>Make<\/b> <i>SONY<\/i> &middot; <b>Camera<\/b> <i>ILCE-7M3<\/i> &middot; <b>Lens Model<\/b> <i>FE 50mm F2.8 Macro<\/i> &middot; <b>Focal Length (35mm)<\/b> <i>50mm<\/i> &middot; <b>Metering Mode<\/b> <i>Multi-segment<\/i> &middot; <b>ISO Equivalent<\/b> <i>6400<\/i> &middot; <b>Exposure Time<\/b> <i>1\/200s<\/i> &middot; <b>Aperture<\/b> <i>ƒ\/16.0<\/i> &middot; <b>Exposure bias<\/b> <i>0 EV<\/i> &middot; <b>Exposure Program<\/b> <i>Manual control<\/i> &middot; <b>White balance<\/b> <i>Auto white balance<\/i> &middot; <b>Flash<\/b> <i>Flash did not fire<\/i>","dates":{"added":1710623416,"dateTaken":1710593095},"fileDate":"2024-03-16T22:28:22.268Z","path":"encoelia-furfuracea-15.webp","imageCaption":"<div class=\"title\">encoelia-furfuracea-15<\/div>","fileSize":14374476,"rights":"Fungarium.info","name":"encoelia-furfuracea-15.webp","category":"image","camera":{"aperture":16.0,"exposureTime":"1\/200s","originalDate":"2024-03-16T14:44:55.0Z","cameraModel":"ILCE-7M3","focalLength35mm":"50mm","cameraMake":"SONY","isoEquivalent":6400,"flash":"Flash did not fire","focalLength":"50mm"}},{"image":{"path":"slides\/encoelia-furfuracea-16.webp","width":2000,"height":1333},"creator":"Boriss Melikjan","thumb":{"path":"thumbs\/encoelia-furfuracea-16.webp","width":512,"height":410},"thumbCaption":"<span class=\"nr\">17<\/span><div class=\"title\">encoelia-furfuracea-16<\/div>","photodata":"<b>Photographer<\/b> <i>Boriss Melikjan<\/i> &middot; <b>Original Date<\/b> <i>3\/16\/24, 2:45\u202FPM<\/i> &middot; <b>Make<\/b> <i>SONY<\/i> &middot; <b>Camera<\/b> <i>ILCE-7M3<\/i> &middot; <b>Lens Model<\/b> <i>FE 50mm F2.8 Macro<\/i> &middot; <b>Focal Length (35mm)<\/b> <i>50mm<\/i> &middot; <b>Metering Mode<\/b> <i>Multi-segment<\/i> &middot; <b>ISO Equivalent<\/b> <i>6400<\/i> &middot; <b>Exposure Time<\/b> <i>1\/200s<\/i> &middot; <b>Aperture<\/b> <i>ƒ\/16.0<\/i> &middot; <b>Exposure bias<\/b> <i>0 EV<\/i> &middot; <b>Exposure Program<\/b> <i>Manual control<\/i> &middot; <b>White balance<\/b> <i>Auto white balance<\/i> &middot; <b>Flash<\/b> <i>Flash did not fire<\/i>","dates":{"added":1710623416,"dateTaken":1710593103},"fileDate":"2024-03-16T22:28:22.703Z","path":"encoelia-furfuracea-16.webp","imageCaption":"<div class=\"title\">encoelia-furfuracea-16<\/div>","fileSize":15368033,"rights":"Fungarium.info","name":"encoelia-furfuracea-16.webp","category":"image","camera":{"aperture":16.0,"exposureTime":"1\/200s","originalDate":"2024-03-16T14:45:03.0Z","cameraModel":"ILCE-7M3","focalLength35mm":"50mm","cameraMake":"SONY","isoEquivalent":6400,"flash":"Flash did not fire","focalLength":"50mm"}},{"image":{"path":"slides\/encoelia-furfuracea-17.webp","width":2000,"height":1333},"creator":"Boriss Melikjan","thumb":{"path":"thumbs\/encoelia-furfuracea-17.webp","width":512,"height":410},"thumbCaption":"<span class=\"nr\">18<\/span><div class=\"title\">encoelia-furfuracea-17<\/div>","photodata":"<b>Photographer<\/b> <i>Boriss Melikjan<\/i> &middot; <b>Original Date<\/b> <i>3\/16\/24, 2:45\u202FPM<\/i> &middot; <b>Make<\/b> <i>SONY<\/i> &middot; <b>Camera<\/b> <i>ILCE-7M3<\/i> &middot; <b>Lens Model<\/b> <i>FE 50mm F2.8 Macro<\/i> &middot; <b>Focal Length (35mm)<\/b> <i>50mm<\/i> &middot; <b>Metering Mode<\/b> <i>Multi-segment<\/i> &middot; <b>ISO Equivalent<\/b> <i>6400<\/i> &middot; <b>Exposure Time<\/b> <i>1\/200s<\/i> &middot; <b>Aperture<\/b> <i>ƒ\/16.0<\/i> &middot; <b>Exposure bias<\/b> <i>0 EV<\/i> &middot; <b>Exposure Program<\/b> <i>Manual control<\/i> &middot; <b>White balance<\/b> <i>Auto white balance<\/i> &middot; <b>Flash<\/b> <i>Flash did not fire<\/i>","dates":{"added":1710623416,"dateTaken":1710593104},"fileDate":"2024-03-16T22:28:22.669Z","path":"encoelia-furfuracea-17.webp","imageCaption":"<div class=\"title\">encoelia-furfuracea-17<\/div>","fileSize":15503685,"rights":"Fungarium.info","name":"encoelia-furfuracea-17.webp","category":"image","camera":{"aperture":16.0,"exposureTime":"1\/200s","originalDate":"2024-03-16T14:45:04.0Z","cameraModel":"ILCE-7M3","focalLength35mm":"50mm","cameraMake":"SONY","isoEquivalent":6400,"flash":"Flash did not fire","focalLength":"50mm"}},{"image":{"path":"slides\/encoelia-furfuracea-18.webp","width":2000,"height":1333},"creator":"Boriss Melikjan","thumb":{"path":"thumbs\/encoelia-furfuracea-18.webp","width":512,"height":410},"thumbCaption":"<span class=\"nr\">19<\/span><div class=\"title\">encoelia-furfuracea-18<\/div>","photodata":"<b>Photographer<\/b> <i>Boriss Melikjan<\/i> &middot; <b>Original Date<\/b> <i>3\/16\/24, 2:45\u202FPM<\/i> &middot; <b>Make<\/b> <i>SONY<\/i> &middot; <b>Camera<\/b> <i>ILCE-7M3<\/i> &middot; <b>Lens Model<\/b> <i>FE 50mm F2.8 Macro<\/i> &middot; <b>Focal Length (35mm)<\/b> <i>50mm<\/i> &middot; <b>Metering Mode<\/b> <i>Multi-segment<\/i> &middot; <b>ISO Equivalent<\/b> <i>6400<\/i> &middot; <b>Exposure Time<\/b> <i>1\/200s<\/i> &middot; <b>Aperture<\/b> <i>ƒ\/16.0<\/i> &middot; <b>Exposure bias<\/b> <i>0 EV<\/i> &middot; <b>Exposure Program<\/b> <i>Manual control<\/i> &middot; <b>White balance<\/b> <i>Auto white balance<\/i> &middot; <b>Flash<\/b> <i>Flash did not fire<\/i>","dates":{"added":1710623416,"dateTaken":1710593107},"fileDate":"2024-03-16T22:28:23.52Z","path":"encoelia-furfuracea-18.webp","imageCaption":"<div class=\"title\">encoelia-furfuracea-18<\/div>","fileSize":15595189,"rights":"Fungarium.info","name":"encoelia-furfuracea-18.webp","category":"image","camera":{"aperture":16.0,"exposureTime":"1\/200s","originalDate":"2024-03-16T14:45:07.0Z","cameraModel":"ILCE-7M3","focalLength35mm":"50mm","cameraMake":"SONY","isoEquivalent":6400,"flash":"Flash did not fire","focalLength":"50mm"}},{"image":{"path":"slides\/encoelia-furfuracea-19.webp","width":2000,"height":1333},"creator":"Boriss Melikjan","thumb":{"path":"thumbs\/encoelia-furfuracea-19.webp","width":512,"height":410},"thumbCaption":"<span class=\"nr\">20<\/span><div class=\"title\">encoelia-furfuracea-19<\/div>","photodata":"<b>Photographer<\/b> <i>Boriss Melikjan<\/i> &middot; <b>Original Date<\/b> <i>3\/16\/24, 2:45\u202FPM<\/i> &middot; <b>Make<\/b> <i>SONY<\/i> &middot; <b>Camera<\/b> <i>ILCE-7M3<\/i> &middot; <b>Lens Model<\/b> <i>FE 50mm F2.8 Macro<\/i> &middot; <b>Focal Length (35mm)<\/b> <i>50mm<\/i> &middot; <b>Metering Mode<\/b> <i>Multi-segment<\/i> &middot; <b>ISO Equivalent<\/b> <i>6400<\/i> &middot; <b>Exposure Time<\/b> <i>1\/200s<\/i> &middot; <b>Aperture<\/b> <i>ƒ\/16.0<\/i> &middot; <b>Exposure bias<\/b> <i>0 EV<\/i> &middot; <b>Exposure Program<\/b> <i>Manual control<\/i> &middot; <b>White balance<\/b> <i>Auto white balance<\/i> &middot; <b>Flash<\/b> <i>Flash did not fire<\/i>","dates":{"added":1710623416,"dateTaken":1710593115},"fileDate":"2024-03-16T22:28:26.372Z","path":"encoelia-furfuracea-19.webp","imageCaption":"<div class=\"title\">encoelia-furfuracea-19<\/div>","fileSize":18920529,"rights":"Fungarium.info","name":"encoelia-furfuracea-19.webp","category":"image","camera":{"aperture":16.0,"exposureTime":"1\/200s","originalDate":"2024-03-16T14:45:15.0Z","cameraModel":"ILCE-7M3","focalLength35mm":"50mm","cameraMake":"SONY","isoEquivalent":6400,"flash":"Flash did not fire","focalLength":"50mm"}},{"image":{"path":"slides\/encoelia-furfuracea-20.webp","width":2000,"height":1333},"creator":"Boriss Melikjan","thumb":{"path":"thumbs\/encoelia-furfuracea-20.webp","width":512,"height":410},"thumbCaption":"<span class=\"nr\">21<\/span><div class=\"title\">encoelia-furfuracea-20<\/div>","photodata":"<b>Photographer<\/b> <i>Boriss Melikjan<\/i> &middot; <b>Original Date<\/b> <i>3\/16\/24, 2:45\u202FPM<\/i> &middot; <b>Make<\/b> <i>SONY<\/i> &middot; <b>Camera<\/b> <i>ILCE-7M3<\/i> &middot; <b>Lens Model<\/b> <i>FE 50mm F2.8 Macro<\/i> &middot; <b>Focal Length (35mm)<\/b> <i>50mm<\/i> &middot; <b>Metering Mode<\/b> <i>Multi-segment<\/i> &middot; <b>ISO Equivalent<\/b> <i>6400<\/i> &middot; <b>Exposure Time<\/b> <i>1\/200s<\/i> &middot; <b>Aperture<\/b> <i>ƒ\/16.0<\/i> &middot; <b>Exposure bias<\/b> <i>0 EV<\/i> &middot; <b>Exposure Program<\/b> <i>Manual control<\/i> &middot; <b>White balance<\/b> <i>Auto white balance<\/i> &middot; <b>Flash<\/b> <i>Flash did not fire<\/i>","dates":{"added":1710623416,"dateTaken":1710593117},"fileDate":"2024-03-16T22:28:26.382Z","path":"encoelia-furfuracea-20.webp","imageCaption":"<div class=\"title\">encoelia-furfuracea-20<\/div>","fileSize":18115588,"rights":"Fungarium.info","name":"encoelia-furfuracea-20.webp","category":"image","camera":{"aperture":16.0,"exposureTime":"1\/200s","originalDate":"2024-03-16T14:45:17.0Z","cameraModel":"ILCE-7M3","focalLength35mm":"50mm","cameraMake":"SONY","isoEquivalent":6400,"flash":"Flash did not fire","focalLength":"50mm"}},{"image":{"path":"slides\/encoelia-furfuracea-21.webp","width":2000,"height":1333},"creator":"Boriss Melikjan","thumb":{"path":"thumbs\/encoelia-furfuracea-21.webp","width":512,"height":410},"thumbCaption":"<span class=\"nr\">22<\/span><div class=\"title\">encoelia-furfuracea-21<\/div>","photodata":"<b>Photographer<\/b> <i>Boriss Melikjan<\/i> &middot; <b>Original Date<\/b> <i>3\/16\/24, 2:46\u202FPM<\/i> &middot; <b>Make<\/b> <i>SONY<\/i> &middot; <b>Camera<\/b> <i>ILCE-7M3<\/i> &middot; <b>Lens Model<\/b> <i>FE 90mm F2.8 Macro G OSS<\/i> &middot; <b>Focal Length (35mm)<\/b> <i>90mm<\/i> &middot; <b>Metering Mode<\/b> <i>Multi-segment<\/i> &middot; <b>ISO Equivalent<\/b> <i>6400<\/i> &middot; <b>Exposure Time<\/b> <i>1\/200s<\/i> &middot; <b>Aperture<\/b> <i>ƒ\/16.0<\/i> &middot; <b>Exposure bias<\/b> <i>0 EV<\/i> &middot; <b>Exposure Program<\/b> <i>Manual control<\/i> &middot; <b>White balance<\/b> <i>Auto white balance<\/i> &middot; <b>Flash<\/b> <i>Flash did not fire<\/i>","dates":{"added":1710623416,"dateTaken":1710593171},"fileDate":"2024-03-16T22:28:26.418Z","path":"encoelia-furfuracea-21.webp","imageCaption":"<div class=\"title\">encoelia-furfuracea-21<\/div>","fileSize":14358140,"rights":"Fungarium.info","name":"encoelia-furfuracea-21.webp","category":"image","camera":{"aperture":16.0,"exposureTime":"1\/200s","originalDate":"2024-03-16T14:46:11.0Z","cameraModel":"ILCE-7M3","focalLength35mm":"90mm","cameraMake":"SONY","isoEquivalent":6400,"flash":"Flash did not fire","focalLength":"90mm"}},{"image":{"path":"slides\/encoelia-furfuracea-22.webp","width":2000,"height":1333},"creator":"Boriss Melikjan","thumb":{"path":"thumbs\/encoelia-furfuracea-22.webp","width":512,"height":410},"thumbCaption":"<span class=\"nr\">23<\/span><div class=\"title\">encoelia-furfuracea-22<\/div>","photodata":"<b>Photographer<\/b> <i>Boriss Melikjan<\/i> &middot; <b>Original Date<\/b> <i>3\/16\/24, 2:46\u202FPM<\/i> &middot; <b>Make<\/b> <i>SONY<\/i> &middot; <b>Camera<\/b> <i>ILCE-7M3<\/i> &middot; <b>Lens Model<\/b> <i>FE 90mm F2.8 Macro G OSS<\/i> &middot; <b>Focal Length (35mm)<\/b> <i>90mm<\/i> &middot; <b>Metering Mode<\/b> <i>Multi-segment<\/i> &middot; <b>ISO Equivalent<\/b> <i>6400<\/i> &middot; <b>Exposure Time<\/b> <i>1\/200s<\/i> &middot; <b>Aperture<\/b> <i>ƒ\/16.0<\/i> &middot; <b>Exposure bias<\/b> <i>0 EV<\/i> &middot; <b>Exposure Program<\/b> <i>Manual control<\/i> &middot; <b>White balance<\/b> <i>Auto white balance<\/i> &middot; <b>Flash<\/b> <i>Flash did not fire<\/i>","dates":{"added":1710623416,"dateTaken":1710593172},"fileDate":"2024-03-16T22:28:26.470Z","path":"encoelia-furfuracea-22.webp","imageCaption":"<div class=\"title\">encoelia-furfuracea-22<\/div>","fileSize":13424506,"rights":"Fungarium.info","name":"encoelia-furfuracea-22.webp","category":"image","camera":{"aperture":16.0,"exposureTime":"1\/200s","originalDate":"2024-03-16T14:46:12.0Z","cameraModel":"ILCE-7M3","focalLength35mm":"90mm","cameraMake":"SONY","isoEquivalent":6400,"flash":"Flash did not fire","focalLength":"90mm"}},{"image":{"path":"slides\/encoelia-furfuracea-23.webp","width":2000,"height":1333},"creator":"Boriss Melikjan","thumb":{"path":"thumbs\/encoelia-furfuracea-23.webp","width":512,"height":410},"thumbCaption":"<span class=\"nr\">24<\/span><div class=\"title\">encoelia-furfuracea-23<\/div>","photodata":"<b>Photographer<\/b> <i>Boriss Melikjan<\/i> &middot; <b>Original Date<\/b> <i>3\/16\/24, 2:46\u202FPM<\/i> &middot; <b>Make<\/b> <i>SONY<\/i> &middot; <b>Camera<\/b> <i>ILCE-7M3<\/i> &middot; <b>Lens Model<\/b> <i>FE 90mm F2.8 Macro G OSS<\/i> &middot; <b>Focal Length (35mm)<\/b> <i>90mm<\/i> &middot; <b>Metering Mode<\/b> <i>Multi-segment<\/i> &middot; <b>ISO Equivalent<\/b> <i>6400<\/i> &middot; <b>Exposure Time<\/b> <i>1\/200s<\/i> &middot; <b>Aperture<\/b> <i>ƒ\/16.0<\/i> &middot; <b>Exposure bias<\/b> <i>0 EV<\/i> &middot; <b>Exposure Program<\/b> <i>Manual control<\/i> &middot; <b>White balance<\/b> <i>Auto white balance<\/i> &middot; <b>Flash<\/b> <i>Flash did not fire<\/i>","dates":{"added":1710623416,"dateTaken":1710593178},"fileDate":"2024-03-16T22:28:26.615Z","path":"encoelia-furfuracea-23.webp","imageCaption":"<div class=\"title\">encoelia-furfuracea-23<\/div>","fileSize":13132364,"rights":"Fungarium.info","name":"encoelia-furfuracea-23.webp","category":"image","camera":{"aperture":16.0,"exposureTime":"1\/200s","originalDate":"2024-03-16T14:46:18.0Z","cameraModel":"ILCE-7M3","focalLength35mm":"90mm","cameraMake":"SONY","isoEquivalent":6400,"flash":"Flash did not fire","focalLength":"90mm"}},{"image":{"path":"slides\/encoelia-furfuracea-24.webp","width":2000,"height":1333},"creator":"Boriss Melikjan","thumb":{"path":"thumbs\/encoelia-furfuracea-24.webp","width":512,"height":410},"thumbCaption":"<span class=\"nr\">25<\/span><div class=\"title\">encoelia-furfuracea-24<\/div>","photodata":"<b>Photographer<\/b> <i>Boriss Melikjan<\/i> &middot; <b>Original Date<\/b> <i>3\/16\/24, 2:46\u202FPM<\/i> &middot; <b>Make<\/b> <i>SONY<\/i> &middot; <b>Camera<\/b> <i>ILCE-7M3<\/i> &middot; <b>Lens Model<\/b> <i>FE 90mm F2.8 Macro G OSS<\/i> &middot; <b>Focal Length (35mm)<\/b> <i>90mm<\/i> &middot; <b>Metering Mode<\/b> <i>Multi-segment<\/i> &middot; <b>ISO Equivalent<\/b> <i>6400<\/i> &middot; <b>Exposure Time<\/b> <i>1\/200s<\/i> &middot; <b>Aperture<\/b> <i>ƒ\/16.0<\/i> &middot; <b>Exposure bias<\/b> <i>0 EV<\/i> &middot; <b>Exposure Program<\/b> <i>Manual control<\/i> &middot; <b>White balance<\/b> <i>Auto white balance<\/i> &middot; <b>Flash<\/b> <i>Flash did not fire<\/i>","dates":{"added":1710623416,"dateTaken":1710593190},"fileDate":"2024-03-16T22:28:26.629Z","path":"encoelia-furfuracea-24.webp","imageCaption":"<div class=\"title\">encoelia-furfuracea-24<\/div>","fileSize":12567463,"rights":"Fungarium.info","name":"encoelia-furfuracea-24.webp","category":"image","camera":{"aperture":16.0,"exposureTime":"1\/200s","originalDate":"2024-03-16T14:46:30.0Z","cameraModel":"ILCE-7M3","focalLength35mm":"90mm","cameraMake":"SONY","isoEquivalent":6400,"flash":"Flash did not fire","focalLength":"90mm"}}],"name":"Энцелия шелушистая - Encoelia furfuracea","comment":"Encoelia furfuracea is a species of fungus known for its distinctive appearance and ecological role. It typically has small fruiting bodies with caps ranging from 0.5 to 2 centimeters in diameter. The caps are irregularly shaped and covered with fine, powdery granules, giving them a dusty or mealy appearance. The coloration of the caps can vary but often ranges from tan to brown.\n\nThis fungus is commonly found growing on decaying wood, particularly hardwoods such as oak and beech, in temperate forests. It plays a vital role in the decomposition of woody debris, helping to recycle nutrients back into the ecosystem. Encoelia furfuracea has a wide distribution and can be found in various parts of North America, Europe, and Asia.\n\nChemically, Encoelia furfuracea produces various compounds, some of which may have potential applications in medicine or industry. Research into the bioactive compounds produced by this fungus is ongoing and may uncover new therapeutic or industrial uses.\n\nThe spores of Encoelia furfuracea are typically released from specialized structures called asci, which are contained within fruiting bodies. These spores are dispersed by wind or other means, allowing the fungus to colonize new habitats and continue its life cycle.\n\nWhile Encoelia furfuracea is not generally considered to be edible, it is an intriguing subject for fungal enthusiasts and researchers due to its unique morphology and ecological importance. As with all wild fungi, proper identification is essential before consumption to avoid potential health risks.","dates":{"added":1710623416,"dateRange":{"0":1710593007,"1":1710622764}},"fileDate":"2024-03-16T23:10:16.713Z","title":" Encoelia furfuracea - Энцелия шелушистая - Spring Hazelcup - Hasel-Kleiebecherling"}