{"path":"%D0%93%D0%BE%D0%B2%D0%BE%D1%80%D1%83%D1%88%D0%BA%D0%B0%20%D0%B1%D0%BB%D0%B0%D0%B3%D0%BE%D1%83%D1%85%D0%B0%D1%8E%D1%89%D0%B0%D1%8F%20-%20Clitocybe%20fragrans","deepCounters":{"total":36,"images":36,"files":36},"counters":{"total":36,"images":36,"files":36},"thumb":{"path":"thumbs\/DSC06760.webp","width":512,"height":410},"thumbCaption":"<h3>Говорушка благоухающая - Clitocybe fragrans<\/h3>","album":{"description":"Fungarium.INFO. Fungarium Photo Collection: Boletes, Toadstools, Agaricomycetes, Fungi, Molds and Myxomycetes.<br\/>\n<br\/><i><b>517<\/b> species in <b>40<\/b> orders and <b>112<\/b> families photographed.<br\/>\n<br\/><b>8503<\/b> images total.<\/i><br\/><br\/>\nTry also other sites: <br\/>\n    <a href=\"https:\/\/herbariuminfo.netlify.app\">Herbarium.INFO<\/a>&nbsp;\u2022&nbsp;\n    <a href=\"https:\/\/plantariuminfo.netlify.app\">Plantarium.INFO<\/a>&nbsp;\u2022&nbsp;\n    <a href=\"https:\/\/fungarium.netlify.app\">Fungarium.INFO<\/a>&nbsp;\u2022&nbsp;\n    <a href=\"https:\/\/lichenarium.netlify.app\">Lichenarium.INFO<\/a>&nbsp;\u2022&nbsp;\n    <a href=\"https:\/\/algaerium.netlify.app\">Algaerium.INFO<\/a>","title":"Fungarium.INFO Fungi: Photo and Catalog"},"objects":[{"image":{"path":"slides\/DSC00807.webp","width":2000,"height":1500},"thumb":{"path":"thumbs\/DSC00807.webp","width":512,"height":410},"thumbCaption":"<span class=\"nr\">1<\/span><div class=\"title\">DSC00807<\/div>","photodata":"<b>Original Date<\/b> <i>9\/9\/20, 2:03\u202FPM<\/i> &middot; <b>Make<\/b> <i>SONY<\/i> &middot; <b>Camera<\/b> <i>DSC-HX90V<\/i> &middot; <b>Lens<\/b> <i>4.1-123mm f\/3.5-6.4<\/i> &middot; <b>Focal Length (35mm)<\/b> <i>38mm<\/i> &middot; <b>Metering Mode<\/b> <i>Spot<\/i> &middot; <b>ISO Equivalent<\/b> <i>80<\/i> &middot; <b>Exposure Time<\/b> <i>1\/500s<\/i> &middot; <b>Aperture<\/b> <i>ƒ\/4<\/i> &middot; <b>Exposure bias<\/b> <i>0 EV<\/i> &middot; <b>Exposure Program<\/b> <i>Manual control<\/i> &middot; <b>White balance<\/b> <i>Manual white balance<\/i> &middot; <b>Flash<\/b> <i>Flash did not fire<\/i> &middot; <b>Resolution<\/b> <i>4896 x 3672<\/i>","dates":{"added":1599674707,"dateTaken":1599649398},"fileDate":"2020-09-09T14:03:18.0Z","path":"DSC00807.webp","imageCaption":"<div class=\"title\">DSC00807<\/div>","fileSize":6969345,"name":"DSC00807.webp","comment":"                               ","location":"59.421540,28.115366","category":"image","camera":{"aperture":4.0,"exposureTime":"1\/500s","originalDate":"2020-09-09T14:03:18.0Z","cameraModel":"DSC-HX90V","location":{"altitude":"19.9 metres","latitude":"59° 25' 17.54\"","lat":59.42154,"long":28.115366,"longitude":"28° 6' 55.32\""},"focalLength35mm":"38mm","resolution":"4896 x 3672","cameraMake":"SONY","isoEquivalent":80,"flash":"Flash did not fire","focalLength":"7mm"}},{"image":{"path":"slides\/DSC00808.webp","width":2000,"height":1500},"thumb":{"path":"thumbs\/DSC00808.webp","width":512,"height":410},"thumbCaption":"<span class=\"nr\">2<\/span><div class=\"title\">DSC00808<\/div>","photodata":"<b>Original Date<\/b> <i>9\/9\/20, 2:03\u202FPM<\/i> &middot; <b>Make<\/b> <i>SONY<\/i> &middot; <b>Camera<\/b> <i>DSC-HX90V<\/i> &middot; <b>Lens<\/b> <i>4.1-123mm f\/3.5-6.4<\/i> &middot; <b>Focal Length (35mm)<\/b> <i>38mm<\/i> &middot; <b>Metering Mode<\/b> <i>Spot<\/i> &middot; <b>ISO Equivalent<\/b> <i>80<\/i> &middot; <b>Exposure Time<\/b> <i>1\/500s<\/i> &middot; <b>Aperture<\/b> <i>ƒ\/4<\/i> &middot; <b>Exposure bias<\/b> <i>0 EV<\/i> &middot; <b>Exposure Program<\/b> <i>Manual control<\/i> &middot; <b>White balance<\/b> <i>Manual white balance<\/i> &middot; <b>Flash<\/b> <i>Flash did not fire<\/i> &middot; <b>Resolution<\/b> <i>4896 x 3672<\/i>","dates":{"added":1599674707,"dateTaken":1599649404},"fileDate":"2020-09-09T14:03:24.0Z","path":"DSC00808.webp","imageCaption":"<div class=\"title\">DSC00808<\/div>","fileSize":6436788,"name":"DSC00808.webp","comment":"                               ","location":"59.421548,28.115415","category":"image","camera":{"aperture":4.0,"exposureTime":"1\/500s","originalDate":"2020-09-09T14:03:24.0Z","cameraModel":"DSC-HX90V","location":{"altitude":"19.9 metres","latitude":"59° 25' 17.57\"","lat":59.421547,"long":28.115416,"longitude":"28° 6' 55.49\""},"focalLength35mm":"38mm","resolution":"4896 x 3672","cameraMake":"SONY","isoEquivalent":80,"flash":"Flash did not fire","focalLength":"7mm"}},{"image":{"path":"slides\/DSC00809.webp","width":2000,"height":1500},"thumb":{"path":"thumbs\/DSC00809.webp","width":512,"height":410},"thumbCaption":"<span class=\"nr\">3<\/span><div class=\"title\">DSC00809<\/div>","photodata":"<b>Original Date<\/b> <i>9\/9\/20, 2:04\u202FPM<\/i> &middot; <b>Make<\/b> <i>SONY<\/i> &middot; <b>Camera<\/b> <i>DSC-HX90V<\/i> &middot; <b>Lens<\/b> <i>4.1-123mm f\/3.5-6.4<\/i> &middot; <b>Focal Length (35mm)<\/b> <i>38mm<\/i> &middot; <b>Metering Mode<\/b> <i>Spot<\/i> &middot; <b>ISO Equivalent<\/b> <i>80<\/i> &middot; <b>Exposure Time<\/b> <i>1\/800s<\/i> &middot; <b>Aperture<\/b> <i>ƒ\/4<\/i> &middot; <b>Exposure bias<\/b> <i>0 EV<\/i> &middot; <b>Exposure Program<\/b> <i>Manual control<\/i> &middot; <b>White balance<\/b> <i>Manual white balance<\/i> &middot; <b>Flash<\/b> <i>Flash did not fire<\/i> &middot; <b>Resolution<\/b> <i>4896 x 3672<\/i>","dates":{"added":1599674707,"dateTaken":1599649458},"fileDate":"2020-09-09T14:04:18.0Z","path":"DSC00809.webp","imageCaption":"<div class=\"title\">DSC00809<\/div>","fileSize":7099426,"name":"DSC00809.webp","comment":"                               ","location":"59.421580,28.115335","category":"image","camera":{"aperture":4.0,"exposureTime":"1\/800s","originalDate":"2020-09-09T14:04:18.0Z","cameraModel":"DSC-HX90V","location":{"altitude":"19.9 metres","latitude":"59° 25' 17.69\"","lat":59.42158,"long":28.115335,"longitude":"28° 6' 55.21\""},"focalLength35mm":"38mm","resolution":"4896 x 3672","cameraMake":"SONY","isoEquivalent":80,"flash":"Flash did not fire","focalLength":"7mm"}},{"image":{"path":"slides\/DSC00810.webp","width":2000,"height":1500},"thumb":{"path":"thumbs\/DSC00810.webp","width":512,"height":410},"thumbCaption":"<span class=\"nr\">4<\/span><div class=\"title\">DSC00810<\/div>","photodata":"<b>Original Date<\/b> <i>9\/9\/20, 2:04\u202FPM<\/i> &middot; <b>Make<\/b> <i>SONY<\/i> &middot; <b>Camera<\/b> <i>DSC-HX90V<\/i> &middot; <b>Lens<\/b> <i>4.1-123mm f\/3.5-6.4<\/i> &middot; <b>Focal Length (35mm)<\/b> <i>38mm<\/i> &middot; <b>Metering Mode<\/b> <i>Spot<\/i> &middot; <b>ISO Equivalent<\/b> <i>80<\/i> &middot; <b>Exposure Time<\/b> <i>1\/800s<\/i> &middot; <b>Aperture<\/b> <i>ƒ\/4<\/i> &middot; <b>Exposure bias<\/b> <i>0 EV<\/i> &middot; <b>Exposure Program<\/b> <i>Manual control<\/i> &middot; <b>White balance<\/b> <i>Manual white balance<\/i> &middot; <b>Flash<\/b> <i>Flash did not fire<\/i> &middot; <b>Resolution<\/b> <i>4896 x 3672<\/i>","dates":{"added":1599674707,"dateTaken":1599649461},"fileDate":"2020-09-09T14:04:20.0Z","path":"DSC00810.webp","imageCaption":"<div class=\"title\">DSC00810<\/div>","fileSize":7210216,"name":"DSC00810.webp","comment":"                               ","location":"59.421580,28.115340","category":"image","camera":{"aperture":4.0,"exposureTime":"1\/800s","originalDate":"2020-09-09T14:04:21.0Z","cameraModel":"DSC-HX90V","location":{"altitude":"19.9 metres","latitude":"59° 25' 17.69\"","lat":59.42158,"long":28.11534,"longitude":"28° 6' 55.22\""},"focalLength35mm":"38mm","resolution":"4896 x 3672","cameraMake":"SONY","isoEquivalent":80,"flash":"Flash did not fire","focalLength":"7mm"}},{"image":{"path":"slides\/DSC00811.webp","width":2000,"height":1500},"thumb":{"path":"thumbs\/DSC00811.webp","width":512,"height":410},"thumbCaption":"<span class=\"nr\">5<\/span><div class=\"title\">DSC00811<\/div>","photodata":"<b>Original Date<\/b> <i>9\/9\/20, 2:04\u202FPM<\/i> &middot; <b>Make<\/b> <i>SONY<\/i> &middot; <b>Camera<\/b> <i>DSC-HX90V<\/i> &middot; <b>Lens<\/b> <i>4.1-123mm f\/3.5-6.4<\/i> &middot; <b>Focal Length (35mm)<\/b> <i>38mm<\/i> &middot; <b>Metering Mode<\/b> <i>Spot<\/i> &middot; <b>ISO Equivalent<\/b> <i>80<\/i> &middot; <b>Exposure Time<\/b> <i>1\/800s<\/i> &middot; <b>Aperture<\/b> <i>ƒ\/4<\/i> &middot; <b>Exposure bias<\/b> <i>0 EV<\/i> &middot; <b>Exposure Program<\/b> <i>Manual control<\/i> &middot; <b>White balance<\/b> <i>Manual white balance<\/i> &middot; <b>Flash<\/b> <i>Flash did not fire<\/i> &middot; <b>Resolution<\/b> <i>4896 x 3672<\/i>","dates":{"added":1599674707,"dateTaken":1599649479},"fileDate":"2020-09-09T14:04:38.0Z","path":"DSC00811.webp","imageCaption":"<div class=\"title\">DSC00811<\/div>","fileSize":6859389,"name":"DSC00811.webp","comment":"                               ","location":"59.421543,28.115286","category":"image","camera":{"aperture":4.0,"exposureTime":"1\/800s","originalDate":"2020-09-09T14:04:39.0Z","cameraModel":"DSC-HX90V","location":{"altitude":"19.7 metres","latitude":"59° 25' 17.55\"","lat":59.421543,"long":28.115286,"longitude":"28° 6' 55.03\""},"focalLength35mm":"38mm","resolution":"4896 x 3672","cameraMake":"SONY","isoEquivalent":80,"flash":"Flash did not fire","focalLength":"7mm"}},{"image":{"path":"slides\/DSC00812.webp","width":2000,"height":1500},"thumb":{"path":"thumbs\/DSC00812.webp","width":512,"height":410},"thumbCaption":"<span class=\"nr\">6<\/span><div class=\"title\">DSC00812<\/div>","photodata":"<b>Original Date<\/b> <i>9\/9\/20, 2:04\u202FPM<\/i> &middot; <b>Make<\/b> <i>SONY<\/i> &middot; <b>Camera<\/b> <i>DSC-HX90V<\/i> &middot; <b>Lens<\/b> <i>4.1-123mm f\/3.5-6.4<\/i> &middot; <b>Focal Length (35mm)<\/b> <i>38mm<\/i> &middot; <b>Metering Mode<\/b> <i>Spot<\/i> &middot; <b>ISO Equivalent<\/b> <i>80<\/i> &middot; <b>Exposure Time<\/b> <i>1\/800s<\/i> &middot; <b>Aperture<\/b> <i>ƒ\/4<\/i> &middot; <b>Exposure bias<\/b> <i>0 EV<\/i> &middot; <b>Exposure Program<\/b> <i>Manual control<\/i> &middot; <b>White balance<\/b> <i>Manual white balance<\/i> &middot; <b>Flash<\/b> <i>Flash did not fire<\/i> &middot; <b>Resolution<\/b> <i>4896 x 3672<\/i>","dates":{"added":1599674707,"dateTaken":1599649481},"fileDate":"2020-09-09T14:04:40.0Z","path":"DSC00812.webp","imageCaption":"<div class=\"title\">DSC00812<\/div>","fileSize":6999441,"name":"DSC00812.webp","comment":"                               ","location":"59.421533,28.115273","category":"image","camera":{"aperture":4.0,"exposureTime":"1\/800s","originalDate":"2020-09-09T14:04:41.0Z","cameraModel":"DSC-HX90V","location":{"altitude":"19.6 metres","latitude":"59° 25' 17.52\"","lat":59.42153,"long":28.115273,"longitude":"28° 6' 54.98\""},"focalLength35mm":"38mm","resolution":"4896 x 3672","cameraMake":"SONY","isoEquivalent":80,"flash":"Flash did not fire","focalLength":"7mm"}},{"image":{"path":"slides\/DSC05839.webp","width":2000,"height":1500},"thumb":{"path":"thumbs\/DSC05839.webp","width":512,"height":410},"thumbCaption":"<span class=\"nr\">7<\/span><div class=\"title\">DSC05839<\/div>","photodata":"<b>Original Date<\/b> <i>8\/28\/21, 3:36\u202FPM<\/i> &middot; <b>Make<\/b> <i>SONY<\/i> &middot; <b>Camera<\/b> <i>DSC-HX90V<\/i> &middot; <b>Lens<\/b> <i>4.1-123mm f\/3.5-6.4<\/i> &middot; <b>Focal Length (35mm)<\/b> <i>24mm<\/i> &middot; <b>Metering Mode<\/b> <i>Spot<\/i> &middot; <b>ISO Equivalent<\/b> <i>80<\/i> &middot; <b>Exposure Time<\/b> <i>1\/250s<\/i> &middot; <b>Aperture<\/b> <i>ƒ\/3.5<\/i> &middot; <b>Exposure bias<\/b> <i>0 EV<\/i> &middot; <b>Exposure Program<\/b> <i>Manual control<\/i> &middot; <b>White balance<\/b> <i>Manual white balance<\/i> &middot; <b>Flash<\/b> <i>Flash did not fire<\/i> &middot; <b>Resolution<\/b> <i>4896 x 3672<\/i>","dates":{"added":1630186865,"dateTaken":1630154212},"fileDate":"2021-08-28T15:36:52.0Z","path":"DSC05839.webp","imageCaption":"<div class=\"title\">DSC05839<\/div>","fileSize":6806291,"name":"DSC05839.webp","comment":"                               ","category":"image","camera":{"aperture":3.5,"exposureTime":"1\/250s","originalDate":"2021-08-28T15:36:52.0Z","cameraModel":"DSC-HX90V","focalLength35mm":"24mm","resolution":"4896 x 3672","cameraMake":"SONY","isoEquivalent":80,"flash":"Flash did not fire","focalLength":"4mm"}},{"image":{"path":"slides\/DSC05840.webp","width":2000,"height":1500},"thumb":{"path":"thumbs\/DSC05840.webp","width":512,"height":410},"thumbCaption":"<span class=\"nr\">8<\/span><div class=\"title\">DSC05840<\/div>","photodata":"<b>Original Date<\/b> <i>8\/28\/21, 3:36\u202FPM<\/i> &middot; <b>Make<\/b> <i>SONY<\/i> &middot; <b>Camera<\/b> <i>DSC-HX90V<\/i> &middot; <b>Lens<\/b> <i>4.1-123mm f\/3.5-6.4<\/i> &middot; <b>Focal Length (35mm)<\/b> <i>24mm<\/i> &middot; <b>Metering Mode<\/b> <i>Spot<\/i> &middot; <b>ISO Equivalent<\/b> <i>80<\/i> &middot; <b>Exposure Time<\/b> <i>1\/250s<\/i> &middot; <b>Aperture<\/b> <i>ƒ\/3.5<\/i> &middot; <b>Exposure bias<\/b> <i>0 EV<\/i> &middot; <b>Exposure Program<\/b> <i>Manual control<\/i> &middot; <b>White balance<\/b> <i>Manual white balance<\/i> &middot; <b>Flash<\/b> <i>Flash did not fire<\/i> &middot; <b>Resolution<\/b> <i>4896 x 3672<\/i>","dates":{"added":1630186865,"dateTaken":1630154215},"fileDate":"2021-08-28T15:36:54.0Z","path":"DSC05840.webp","imageCaption":"<div class=\"title\">DSC05840<\/div>","fileSize":9035111,"name":"DSC05840.webp","comment":"                               ","location":"59.352013,24.708153","category":"image","camera":{"aperture":3.5,"exposureTime":"1\/250s","originalDate":"2021-08-28T15:36:55.0Z","cameraModel":"DSC-HX90V","location":{"altitude":"33 metres","latitude":"59° 21' 7.25\"","lat":59.352013,"long":24.708153,"longitude":"24° 42' 29.35\""},"focalLength35mm":"24mm","resolution":"4896 x 3672","cameraMake":"SONY","isoEquivalent":80,"flash":"Flash did not fire","focalLength":"4mm"}},{"image":{"path":"slides\/DSC05841.webp","width":2000,"height":1500},"thumb":{"path":"thumbs\/DSC05841.webp","width":512,"height":410},"thumbCaption":"<span class=\"nr\">9<\/span><div class=\"title\">DSC05841<\/div>","photodata":"<b>Original Date<\/b> <i>8\/28\/21, 3:37\u202FPM<\/i> &middot; <b>Make<\/b> <i>SONY<\/i> &middot; <b>Camera<\/b> <i>DSC-HX90V<\/i> &middot; <b>Lens<\/b> <i>4.1-123mm f\/3.5-6.4<\/i> &middot; <b>Focal Length (35mm)<\/b> <i>24mm<\/i> &middot; <b>Metering Mode<\/b> <i>Spot<\/i> &middot; <b>ISO Equivalent<\/b> <i>80<\/i> &middot; <b>Exposure Time<\/b> <i>1\/250s<\/i> &middot; <b>Aperture<\/b> <i>ƒ\/3.5<\/i> &middot; <b>Exposure bias<\/b> <i>0 EV<\/i> &middot; <b>Exposure Program<\/b> <i>Manual control<\/i> &middot; <b>White balance<\/b> <i>Manual white balance<\/i> &middot; <b>Flash<\/b> <i>Flash did not fire<\/i> &middot; <b>Resolution<\/b> <i>4896 x 3672<\/i>","dates":{"added":1630186865,"dateTaken":1630154220},"fileDate":"2021-08-28T15:37:00.0Z","path":"DSC05841.webp","imageCaption":"<div class=\"title\">DSC05841<\/div>","fileSize":6082377,"name":"DSC05841.webp","comment":"                               ","location":"59.352070,24.708285","category":"image","camera":{"aperture":3.5,"exposureTime":"1\/250s","originalDate":"2021-08-28T15:37:00.0Z","cameraModel":"DSC-HX90V","location":{"altitude":"56.7 metres","latitude":"59° 21' 7.45\"","lat":59.35207,"long":24.708284,"longitude":"24° 42' 29.83\""},"focalLength35mm":"24mm","resolution":"4896 x 3672","cameraMake":"SONY","isoEquivalent":80,"flash":"Flash did not fire","focalLength":"4mm"}},{"image":{"path":"slides\/DSC05842.webp","width":2000,"height":1500},"thumb":{"path":"thumbs\/DSC05842.webp","width":512,"height":410},"thumbCaption":"<span class=\"nr\">10<\/span><div class=\"title\">DSC05842<\/div>","photodata":"<b>Original Date<\/b> <i>8\/28\/21, 3:37\u202FPM<\/i> &middot; <b>Make<\/b> <i>SONY<\/i> &middot; <b>Camera<\/b> <i>DSC-HX90V<\/i> &middot; <b>Lens<\/b> <i>4.1-123mm f\/3.5-6.4<\/i> &middot; <b>Focal Length (35mm)<\/b> <i>24mm<\/i> &middot; <b>Metering Mode<\/b> <i>Spot<\/i> &middot; <b>ISO Equivalent<\/b> <i>80<\/i> &middot; <b>Exposure Time<\/b> <i>1\/160s<\/i> &middot; <b>Aperture<\/b> <i>ƒ\/3.5<\/i> &middot; <b>Exposure bias<\/b> <i>0 EV<\/i> &middot; <b>Exposure Program<\/b> <i>Manual control<\/i> &middot; <b>White balance<\/b> <i>Manual white balance<\/i> &middot; <b>Flash<\/b> <i>Flash did not fire<\/i> &middot; <b>Resolution<\/b> <i>4896 x 3672<\/i>","dates":{"added":1630186865,"dateTaken":1630154251},"fileDate":"2021-08-28T15:37:30.0Z","path":"DSC05842.webp","imageCaption":"<div class=\"title\">DSC05842<\/div>","fileSize":5819655,"name":"DSC05842.webp","comment":"                               ","location":"59.352025,24.708278","category":"image","camera":{"aperture":3.5,"exposureTime":"1\/160s","originalDate":"2021-08-28T15:37:31.0Z","cameraModel":"DSC-HX90V","location":{"altitude":"54.4 metres","latitude":"59° 21' 7.29\"","lat":59.352024,"long":24.708279,"longitude":"24° 42' 29.8\""},"focalLength35mm":"24mm","resolution":"4896 x 3672","cameraMake":"SONY","isoEquivalent":80,"flash":"Flash did not fire","focalLength":"4mm"}},{"image":{"path":"slides\/DSC05843.webp","width":2000,"height":1500},"thumb":{"path":"thumbs\/DSC05843.webp","width":512,"height":410},"thumbCaption":"<span class=\"nr\">11<\/span><div class=\"title\">DSC05843<\/div>","photodata":"<b>Original Date<\/b> <i>8\/28\/21, 3:37\u202FPM<\/i> &middot; <b>Make<\/b> <i>SONY<\/i> &middot; <b>Camera<\/b> <i>DSC-HX90V<\/i> &middot; <b>Lens<\/b> <i>4.1-123mm f\/3.5-6.4<\/i> &middot; <b>Focal Length (35mm)<\/b> <i>24mm<\/i> &middot; <b>Metering Mode<\/b> <i>Spot<\/i> &middot; <b>ISO Equivalent<\/b> <i>80<\/i> &middot; <b>Exposure Time<\/b> <i>1\/160s<\/i> &middot; <b>Aperture<\/b> <i>ƒ\/3.5<\/i> &middot; <b>Exposure bias<\/b> <i>0 EV<\/i> &middot; <b>Exposure Program<\/b> <i>Manual control<\/i> &middot; <b>White balance<\/b> <i>Manual white balance<\/i> &middot; <b>Flash<\/b> <i>Flash did not fire<\/i> &middot; <b>Resolution<\/b> <i>4896 x 3672<\/i>","dates":{"added":1630186865,"dateTaken":1630154259},"fileDate":"2021-08-28T15:37:38.0Z","path":"DSC05843.webp","imageCaption":"<div class=\"title\">DSC05843<\/div>","fileSize":7557848,"name":"DSC05843.webp","comment":"                               ","location":"59.352021,24.708278","category":"image","camera":{"aperture":3.5,"exposureTime":"1\/160s","originalDate":"2021-08-28T15:37:39.0Z","cameraModel":"DSC-HX90V","location":{"altitude":"52.1 metres","latitude":"59° 21' 7.28\"","lat":59.35202,"long":24.708279,"longitude":"24° 42' 29.8\""},"focalLength35mm":"24mm","resolution":"4896 x 3672","cameraMake":"SONY","isoEquivalent":80,"flash":"Flash did not fire","focalLength":"4mm"}},{"image":{"path":"slides\/DSC05844.webp","width":2000,"height":1500},"thumb":{"path":"thumbs\/DSC05844.webp","width":512,"height":410},"thumbCaption":"<span class=\"nr\">12<\/span><div class=\"title\">DSC05844<\/div>","photodata":"<b>Original Date<\/b> <i>8\/28\/21, 3:37\u202FPM<\/i> &middot; <b>Make<\/b> <i>SONY<\/i> &middot; <b>Camera<\/b> <i>DSC-HX90V<\/i> &middot; <b>Lens<\/b> <i>4.1-123mm f\/3.5-6.4<\/i> &middot; <b>Focal Length (35mm)<\/b> <i>24mm<\/i> &middot; <b>Metering Mode<\/b> <i>Spot<\/i> &middot; <b>ISO Equivalent<\/b> <i>80<\/i> &middot; <b>Exposure Time<\/b> <i>1\/160s<\/i> &middot; <b>Aperture<\/b> <i>ƒ\/3.5<\/i> &middot; <b>Exposure bias<\/b> <i>0 EV<\/i> &middot; <b>Exposure Program<\/b> <i>Manual control<\/i> &middot; <b>White balance<\/b> <i>Manual white balance<\/i> &middot; <b>Flash<\/b> <i>Flash did not fire<\/i> &middot; <b>Resolution<\/b> <i>4896 x 3672<\/i>","dates":{"added":1630186865,"dateTaken":1630154266},"fileDate":"2021-08-28T15:37:46.0Z","path":"DSC05844.webp","imageCaption":"<div class=\"title\">DSC05844<\/div>","fileSize":6041134,"name":"DSC05844.webp","comment":"                               ","location":"59.352026,24.708276","category":"image","camera":{"aperture":3.5,"exposureTime":"1\/160s","originalDate":"2021-08-28T15:37:46.0Z","cameraModel":"DSC-HX90V","location":{"altitude":"52.3 metres","latitude":"59° 21' 7.29\"","lat":59.352028,"long":24.708277,"longitude":"24° 42' 29.79\""},"focalLength35mm":"24mm","resolution":"4896 x 3672","cameraMake":"SONY","isoEquivalent":80,"flash":"Flash did not fire","focalLength":"4mm"}},{"image":{"path":"slides\/DSC05845.webp","width":2000,"height":1500},"thumb":{"path":"thumbs\/DSC05845.webp","width":512,"height":410},"thumbCaption":"<span class=\"nr\">13<\/span><div class=\"title\">DSC05845<\/div>","photodata":"<b>Original Date<\/b> <i>8\/28\/21, 3:37\u202FPM<\/i> &middot; <b>Make<\/b> <i>SONY<\/i> &middot; <b>Camera<\/b> <i>DSC-HX90V<\/i> &middot; <b>Lens<\/b> <i>4.1-123mm f\/3.5-6.4<\/i> &middot; <b>Focal Length (35mm)<\/b> <i>24mm<\/i> &middot; <b>Metering Mode<\/b> <i>Spot<\/i> &middot; <b>ISO Equivalent<\/b> <i>80<\/i> &middot; <b>Exposure Time<\/b> <i>1\/160s<\/i> &middot; <b>Aperture<\/b> <i>ƒ\/3.5<\/i> &middot; <b>Exposure bias<\/b> <i>0 EV<\/i> &middot; <b>Exposure Program<\/b> <i>Manual control<\/i> &middot; <b>White balance<\/b> <i>Manual white balance<\/i> &middot; <b>Flash<\/b> <i>Flash did not fire<\/i> &middot; <b>Resolution<\/b> <i>4896 x 3672<\/i>","dates":{"added":1630186865,"dateTaken":1630154271},"fileDate":"2021-08-28T15:37:50.0Z","path":"DSC05845.webp","imageCaption":"<div class=\"title\">DSC05845<\/div>","fileSize":7475810,"name":"DSC05845.webp","comment":"                               ","location":"59.352036,24.708271","category":"image","camera":{"aperture":3.5,"exposureTime":"1\/160s","originalDate":"2021-08-28T15:37:51.0Z","cameraModel":"DSC-HX90V","location":{"altitude":"52.8 metres","latitude":"59° 21' 7.33\"","lat":59.352036,"long":24.708271,"longitude":"24° 42' 29.78\""},"focalLength35mm":"24mm","resolution":"4896 x 3672","cameraMake":"SONY","isoEquivalent":80,"flash":"Flash did not fire","focalLength":"4mm"}},{"image":{"path":"slides\/DSC05846.webp","width":2000,"height":1500},"thumb":{"path":"thumbs\/DSC05846.webp","width":512,"height":410},"thumbCaption":"<span class=\"nr\">14<\/span><div class=\"title\">DSC05846<\/div>","photodata":"<b>Original Date<\/b> <i>8\/28\/21, 3:38\u202FPM<\/i> &middot; <b>Make<\/b> <i>SONY<\/i> &middot; <b>Camera<\/b> <i>DSC-HX90V<\/i> &middot; <b>Lens<\/b> <i>4.1-123mm f\/3.5-6.4<\/i> &middot; <b>Focal Length (35mm)<\/b> <i>24mm<\/i> &middot; <b>Metering Mode<\/b> <i>Spot<\/i> &middot; <b>ISO Equivalent<\/b> <i>80<\/i> &middot; <b>Exposure Time<\/b> <i>1\/160s<\/i> &middot; <b>Aperture<\/b> <i>ƒ\/3.5<\/i> &middot; <b>Exposure bias<\/b> <i>0 EV<\/i> &middot; <b>Exposure Program<\/b> <i>Manual control<\/i> &middot; <b>White balance<\/b> <i>Manual white balance<\/i> &middot; <b>Flash<\/b> <i>Flash did not fire<\/i> &middot; <b>Resolution<\/b> <i>4896 x 3672<\/i>","dates":{"added":1630186865,"dateTaken":1630154281},"fileDate":"2021-08-28T15:38:00.0Z","path":"DSC05846.webp","imageCaption":"<div class=\"title\">DSC05846<\/div>","fileSize":7297723,"name":"DSC05846.webp","comment":"                               ","location":"59.352043,24.708260","category":"image","camera":{"aperture":3.5,"exposureTime":"1\/160s","originalDate":"2021-08-28T15:38:01.0Z","cameraModel":"DSC-HX90V","location":{"altitude":"53.2 metres","latitude":"59° 21' 7.35\"","lat":59.352043,"long":24.70826,"longitude":"24° 42' 29.74\""},"focalLength35mm":"24mm","resolution":"4896 x 3672","cameraMake":"SONY","isoEquivalent":80,"flash":"Flash did not fire","focalLength":"4mm"}},{"image":{"path":"slides\/DSC05847.webp","width":2000,"height":1500},"thumb":{"path":"thumbs\/DSC05847.webp","width":512,"height":410},"thumbCaption":"<span class=\"nr\">15<\/span><div class=\"title\">DSC05847<\/div>","photodata":"<b>Original Date<\/b> <i>8\/28\/21, 3:38\u202FPM<\/i> &middot; <b>Make<\/b> <i>SONY<\/i> &middot; <b>Camera<\/b> <i>DSC-HX90V<\/i> &middot; <b>Lens<\/b> <i>4.1-123mm f\/3.5-6.4<\/i> &middot; <b>Focal Length (35mm)<\/b> <i>24mm<\/i> &middot; <b>Metering Mode<\/b> <i>Spot<\/i> &middot; <b>ISO Equivalent<\/b> <i>80<\/i> &middot; <b>Exposure Time<\/b> <i>1\/160s<\/i> &middot; <b>Aperture<\/b> <i>ƒ\/3.5<\/i> &middot; <b>Exposure bias<\/b> <i>0 EV<\/i> &middot; <b>Exposure Program<\/b> <i>Manual control<\/i> &middot; <b>White balance<\/b> <i>Manual white balance<\/i> &middot; <b>Flash<\/b> <i>Flash did not fire<\/i> &middot; <b>Resolution<\/b> <i>4896 x 3672<\/i>","dates":{"added":1630186865,"dateTaken":1630154283},"fileDate":"2021-08-28T15:38:02.0Z","path":"DSC05847.webp","imageCaption":"<div class=\"title\">DSC05847<\/div>","fileSize":7365497,"name":"DSC05847.webp","comment":"                               ","location":"59.352045,24.708261","category":"image","camera":{"aperture":3.5,"exposureTime":"1\/160s","originalDate":"2021-08-28T15:38:03.0Z","cameraModel":"DSC-HX90V","location":{"altitude":"53.2 metres","latitude":"59° 21' 7.36\"","lat":59.352043,"long":24.708261,"longitude":"24° 42' 29.74\""},"focalLength35mm":"24mm","resolution":"4896 x 3672","cameraMake":"SONY","isoEquivalent":80,"flash":"Flash did not fire","focalLength":"4mm"}},{"image":{"path":"slides\/DSC05848.webp","width":2000,"height":1500},"thumb":{"path":"thumbs\/DSC05848.webp","width":512,"height":410},"thumbCaption":"<span class=\"nr\">16<\/span><div class=\"title\">DSC05848<\/div>","photodata":"<b>Original Date<\/b> <i>8\/28\/21, 3:39\u202FPM<\/i> &middot; <b>Make<\/b> <i>SONY<\/i> &middot; <b>Camera<\/b> <i>DSC-HX90V<\/i> &middot; <b>Lens<\/b> <i>4.1-123mm f\/3.5-6.4<\/i> &middot; <b>Focal Length (35mm)<\/b> <i>24mm<\/i> &middot; <b>Metering Mode<\/b> <i>Spot<\/i> &middot; <b>ISO Equivalent<\/b> <i>200<\/i> &middot; <b>Exposure Time<\/b> <i>1\/160s<\/i> &middot; <b>Aperture<\/b> <i>ƒ\/3.5<\/i> &middot; <b>Exposure bias<\/b> <i>0 EV<\/i> &middot; <b>Exposure Program<\/b> <i>Manual control<\/i> &middot; <b>White balance<\/b> <i>Manual white balance<\/i> &middot; <b>Flash<\/b> <i>Flash did not fire<\/i> &middot; <b>Resolution<\/b> <i>4896 x 3672<\/i>","dates":{"added":1630186865,"dateTaken":1630154378},"fileDate":"2021-08-28T15:39:38.0Z","path":"DSC05848.webp","imageCaption":"<div class=\"title\">DSC05848<\/div>","fileSize":8377977,"name":"DSC05848.webp","comment":"                               ","category":"image","camera":{"aperture":3.5,"exposureTime":"1\/160s","originalDate":"2021-08-28T15:39:38.0Z","cameraModel":"DSC-HX90V","focalLength35mm":"24mm","resolution":"4896 x 3672","cameraMake":"SONY","isoEquivalent":200,"flash":"Flash did not fire","focalLength":"4mm"}},{"image":{"path":"slides\/DSC05849.webp","width":2000,"height":1500},"thumb":{"path":"thumbs\/DSC05849.webp","width":512,"height":410},"thumbCaption":"<span class=\"nr\">17<\/span><div class=\"title\">DSC05849<\/div>","photodata":"<b>Original Date<\/b> <i>8\/28\/21, 3:39\u202FPM<\/i> &middot; <b>Make<\/b> <i>SONY<\/i> &middot; <b>Camera<\/b> <i>DSC-HX90V<\/i> &middot; <b>Lens<\/b> <i>4.1-123mm f\/3.5-6.4<\/i> &middot; <b>Focal Length (35mm)<\/b> <i>24mm<\/i> &middot; <b>Metering Mode<\/b> <i>Spot<\/i> &middot; <b>ISO Equivalent<\/b> <i>200<\/i> &middot; <b>Exposure Time<\/b> <i>1\/160s<\/i> &middot; <b>Aperture<\/b> <i>ƒ\/3.5<\/i> &middot; <b>Exposure bias<\/b> <i>0 EV<\/i> &middot; <b>Exposure Program<\/b> <i>Manual control<\/i> &middot; <b>White balance<\/b> <i>Manual white balance<\/i> &middot; <b>Flash<\/b> <i>Flash did not fire<\/i> &middot; <b>Resolution<\/b> <i>4896 x 3672<\/i>","dates":{"added":1630186865,"dateTaken":1630154381},"fileDate":"2021-08-28T15:39:40.0Z","path":"DSC05849.webp","imageCaption":"<div class=\"title\">DSC05849<\/div>","fileSize":6418087,"name":"DSC05849.webp","comment":"                               ","location":"59.351731,24.708270","category":"image","camera":{"aperture":3.5,"exposureTime":"1\/160s","originalDate":"2021-08-28T15:39:41.0Z","cameraModel":"DSC-HX90V","location":{"altitude":"48.4 metres","latitude":"59° 21' 6.23\"","lat":59.35173,"long":24.70827,"longitude":"24° 42' 29.77\""},"focalLength35mm":"24mm","resolution":"4896 x 3672","cameraMake":"SONY","isoEquivalent":200,"flash":"Flash did not fire","focalLength":"4mm"}},{"image":{"path":"slides\/DSC06066.webp","width":2000,"height":1500},"thumb":{"path":"thumbs\/DSC06066.webp","width":512,"height":410},"thumbCaption":"<span class=\"nr\">18<\/span><div class=\"title\">DSC06066<\/div>","photodata":"<b>Original Date<\/b> <i>9\/19\/22, 4:07\u202FPM<\/i> &middot; <b>Make<\/b> <i>SONY<\/i> &middot; <b>Camera<\/b> <i>DSC-HX99<\/i> &middot; <b>Lens<\/b> <i>4.25-118mm f\/3.5-6.4<\/i> &middot; <b>Focal Length (35mm)<\/b> <i>24mm<\/i> &middot; <b>Metering Mode<\/b> <i>Multi-segment<\/i> &middot; <b>ISO Equivalent<\/b> <i>100<\/i> &middot; <b>Exposure Time<\/b> <i>1\/160s<\/i> &middot; <b>Aperture<\/b> <i>ƒ\/4.5<\/i> &middot; <b>Exposure bias<\/b> <i>0 EV<\/i> &middot; <b>Exposure Program<\/b> <i>Manual control<\/i> &middot; <b>White balance<\/b> <i>Manual white balance<\/i> &middot; <b>Flash<\/b> <i>Flash did not fire<\/i> &middot; <b>Resolution<\/b> <i>4896 x 3672<\/i>","dates":{"added":1664064137,"dateTaken":1663592827},"fileDate":"2022-09-19T16:07:06.0Z","path":"DSC06066.webp","imageCaption":"<div class=\"title\">DSC06066<\/div>","fileSize":13862309,"name":"DSC06066.webp","comment":"                               ","location":"57.985682,27.623079","category":"image","camera":{"aperture":4.5,"exposureTime":"1\/160s","originalDate":"2022-09-19T16:07:07.0Z","cameraModel":"DSC-HX99","location":{"latitude":"57° 59' 8.45\"","lat":57.985683,"long":27.62308,"longitude":"27° 37' 23.09\""},"focalLength35mm":"24mm","resolution":"4896 x 3672","cameraMake":"SONY","isoEquivalent":100,"flash":"Flash did not fire","focalLength":"4mm"}},{"image":{"path":"slides\/DSC06069.webp","width":2000,"height":1500},"thumb":{"path":"thumbs\/DSC06069.webp","width":512,"height":410},"thumbCaption":"<span class=\"nr\">19<\/span><div class=\"title\">DSC06069<\/div>","photodata":"<b>Original Date<\/b> <i>9\/19\/22, 4:07\u202FPM<\/i> &middot; <b>Make<\/b> <i>SONY<\/i> &middot; <b>Camera<\/b> <i>DSC-HX99<\/i> &middot; <b>Lens<\/b> <i>4.25-118mm f\/3.5-6.4<\/i> &middot; <b>Focal Length (35mm)<\/b> <i>24mm<\/i> &middot; <b>Metering Mode<\/b> <i>Multi-segment<\/i> &middot; <b>ISO Equivalent<\/b> <i>100<\/i> &middot; <b>Exposure Time<\/b> <i>1\/160s<\/i> &middot; <b>Aperture<\/b> <i>ƒ\/4.5<\/i> &middot; <b>Exposure bias<\/b> <i>0 EV<\/i> &middot; <b>Exposure Program<\/b> <i>Manual control<\/i> &middot; <b>White balance<\/b> <i>Manual white balance<\/i> &middot; <b>Flash<\/b> <i>Flash did not fire<\/i> &middot; <b>Resolution<\/b> <i>4896 x 3672<\/i>","dates":{"added":1664064137,"dateTaken":1663592830},"fileDate":"2022-09-19T16:07:10.0Z","path":"DSC06069.webp","imageCaption":"<div class=\"title\">DSC06069<\/div>","fileSize":18984045,"name":"DSC06069.webp","comment":"                               ","location":"57.985661,27.623052","category":"image","camera":{"aperture":4.5,"exposureTime":"1\/160s","originalDate":"2022-09-19T16:07:10.0Z","cameraModel":"DSC-HX99","location":{"latitude":"57° 59' 8.38\"","lat":57.98566,"long":27.623053,"longitude":"27° 37' 22.99\""},"focalLength35mm":"24mm","resolution":"4896 x 3672","cameraMake":"SONY","isoEquivalent":100,"flash":"Flash did not fire","focalLength":"4mm"}},{"image":{"path":"slides\/DSC06072.webp","width":2000,"height":1500},"thumb":{"path":"thumbs\/DSC06072.webp","width":512,"height":410},"thumbCaption":"<span class=\"nr\">20<\/span><div class=\"title\">DSC06072<\/div>","photodata":"<b>Original Date<\/b> <i>9\/19\/22, 4:07\u202FPM<\/i> &middot; <b>Make<\/b> <i>SONY<\/i> &middot; <b>Camera<\/b> <i>DSC-HX99<\/i> &middot; <b>Lens<\/b> <i>4.25-118mm f\/3.5-6.4<\/i> &middot; <b>Focal Length (35mm)<\/b> <i>24mm<\/i> &middot; <b>Metering Mode<\/b> <i>Multi-segment<\/i> &middot; <b>ISO Equivalent<\/b> <i>100<\/i> &middot; <b>Exposure Time<\/b> <i>1\/160s<\/i> &middot; <b>Aperture<\/b> <i>ƒ\/4.5<\/i> &middot; <b>Exposure bias<\/b> <i>0 EV<\/i> &middot; <b>Exposure Program<\/b> <i>Manual control<\/i> &middot; <b>White balance<\/b> <i>Manual white balance<\/i> &middot; <b>Flash<\/b> <i>Flash did not fire<\/i> &middot; <b>Resolution<\/b> <i>4896 x 3672<\/i>","dates":{"added":1664064137,"dateTaken":1663592837},"fileDate":"2022-09-19T16:07:16.0Z","path":"DSC06072.webp","imageCaption":"<div class=\"title\">DSC06072<\/div>","fileSize":17260277,"name":"DSC06072.webp","comment":"                               ","location":"57.985644,27.623035","category":"image","camera":{"aperture":4.5,"exposureTime":"1\/160s","originalDate":"2022-09-19T16:07:17.0Z","cameraModel":"DSC-HX99","location":{"latitude":"57° 59' 8.32\"","lat":57.985645,"long":27.623035,"longitude":"27° 37' 22.93\""},"focalLength35mm":"24mm","resolution":"4896 x 3672","cameraMake":"SONY","isoEquivalent":100,"flash":"Flash did not fire","focalLength":"4mm"}},{"image":{"path":"slides\/DSC06075.webp","width":2000,"height":1500},"thumb":{"path":"thumbs\/DSC06075.webp","width":512,"height":410},"thumbCaption":"<span class=\"nr\">21<\/span><div class=\"title\">DSC06075<\/div>","photodata":"<b>Original Date<\/b> <i>9\/19\/22, 4:07\u202FPM<\/i> &middot; <b>Make<\/b> <i>SONY<\/i> &middot; <b>Camera<\/b> <i>DSC-HX99<\/i> &middot; <b>Lens<\/b> <i>4.25-118mm f\/3.5-6.4<\/i> &middot; <b>Focal Length (35mm)<\/b> <i>24mm<\/i> &middot; <b>Metering Mode<\/b> <i>Multi-segment<\/i> &middot; <b>ISO Equivalent<\/b> <i>100<\/i> &middot; <b>Exposure Time<\/b> <i>1\/125s<\/i> &middot; <b>Aperture<\/b> <i>ƒ\/4.5<\/i> &middot; <b>Exposure bias<\/b> <i>0 EV<\/i> &middot; <b>Exposure Program<\/b> <i>Manual control<\/i> &middot; <b>White balance<\/b> <i>Manual white balance<\/i> &middot; <b>Flash<\/b> <i>Flash did not fire<\/i> &middot; <b>Resolution<\/b> <i>4896 x 3672<\/i>","dates":{"added":1664064137,"dateTaken":1663592840},"fileDate":"2022-09-19T16:07:20.0Z","path":"DSC06075.webp","imageCaption":"<div class=\"title\">DSC06075<\/div>","fileSize":17256041,"name":"DSC06075.webp","comment":"                               ","location":"57.985644,27.623035","category":"image","camera":{"aperture":4.5,"exposureTime":"1\/125s","originalDate":"2022-09-19T16:07:20.0Z","cameraModel":"DSC-HX99","location":{"latitude":"57° 59' 8.32\"","lat":57.985645,"long":27.623035,"longitude":"27° 37' 22.93\""},"focalLength35mm":"24mm","resolution":"4896 x 3672","cameraMake":"SONY","isoEquivalent":100,"flash":"Flash did not fire","focalLength":"4mm"}},{"image":{"path":"slides\/DSC06078.webp","width":2000,"height":1500},"thumb":{"path":"thumbs\/DSC06078.webp","width":512,"height":410},"thumbCaption":"<span class=\"nr\">22<\/span><div class=\"title\">DSC06078<\/div>","photodata":"<b>Original Date<\/b> <i>9\/19\/22, 4:07\u202FPM<\/i> &middot; <b>Make<\/b> <i>SONY<\/i> &middot; <b>Camera<\/b> <i>DSC-HX99<\/i> &middot; <b>Lens<\/b> <i>4.25-118mm f\/3.5-6.4<\/i> &middot; <b>Focal Length (35mm)<\/b> <i>24mm<\/i> &middot; <b>Metering Mode<\/b> <i>Multi-segment<\/i> &middot; <b>ISO Equivalent<\/b> <i>100<\/i> &middot; <b>Exposure Time<\/b> <i>1\/160s<\/i> &middot; <b>Aperture<\/b> <i>ƒ\/4.5<\/i> &middot; <b>Exposure bias<\/b> <i>0 EV<\/i> &middot; <b>Exposure Program<\/b> <i>Manual control<\/i> &middot; <b>White balance<\/b> <i>Manual white balance<\/i> &middot; <b>Flash<\/b> <i>Flash did not fire<\/i> &middot; <b>Resolution<\/b> <i>4896 x 3672<\/i>","dates":{"added":1664064137,"dateTaken":1663592848},"fileDate":"2022-09-19T16:07:28.0Z","path":"DSC06078.webp","imageCaption":"<div class=\"title\">DSC06078<\/div>","fileSize":12138340,"name":"DSC06078.webp","comment":"                               ","location":"57.985644,27.623035","category":"image","camera":{"aperture":4.5,"exposureTime":"1\/160s","originalDate":"2022-09-19T16:07:28.0Z","cameraModel":"DSC-HX99","location":{"latitude":"57° 59' 8.32\"","lat":57.985645,"long":27.623035,"longitude":"27° 37' 22.93\""},"focalLength35mm":"24mm","resolution":"4896 x 3672","cameraMake":"SONY","isoEquivalent":100,"flash":"Flash did not fire","focalLength":"4mm"}},{"image":{"path":"slides\/DSC06081.webp","width":2000,"height":1500},"thumb":{"path":"thumbs\/DSC06081.webp","width":512,"height":410},"thumbCaption":"<span class=\"nr\">23<\/span><div class=\"title\">DSC06081<\/div>","photodata":"<b>Original Date<\/b> <i>9\/19\/22, 4:07\u202FPM<\/i> &middot; <b>Make<\/b> <i>SONY<\/i> &middot; <b>Camera<\/b> <i>DSC-HX99<\/i> &middot; <b>Lens<\/b> <i>4.25-118mm f\/3.5-6.4<\/i> &middot; <b>Focal Length (35mm)<\/b> <i>24mm<\/i> &middot; <b>Metering Mode<\/b> <i>Multi-segment<\/i> &middot; <b>ISO Equivalent<\/b> <i>100<\/i> &middot; <b>Exposure Time<\/b> <i>1\/160s<\/i> &middot; <b>Aperture<\/b> <i>ƒ\/4.5<\/i> &middot; <b>Exposure bias<\/b> <i>0 EV<\/i> &middot; <b>Exposure Program<\/b> <i>Manual control<\/i> &middot; <b>White balance<\/b> <i>Manual white balance<\/i> &middot; <b>Flash<\/b> <i>Flash did not fire<\/i> &middot; <b>Resolution<\/b> <i>4896 x 3672<\/i>","dates":{"added":1664064137,"dateTaken":1663592878},"fileDate":"2022-09-19T16:07:58.0Z","path":"DSC06081.webp","imageCaption":"<div class=\"title\">DSC06081<\/div>","fileSize":12569436,"name":"DSC06081.webp","comment":"                               ","location":"57.985725,27.623114","category":"image","camera":{"aperture":4.5,"exposureTime":"1\/160s","originalDate":"2022-09-19T16:07:58.0Z","cameraModel":"DSC-HX99","location":{"latitude":"57° 59' 8.61\"","lat":57.985725,"long":27.623114,"longitude":"27° 37' 23.21\""},"focalLength35mm":"24mm","resolution":"4896 x 3672","cameraMake":"SONY","isoEquivalent":100,"flash":"Flash did not fire","focalLength":"4mm"}},{"image":{"path":"slides\/DSC06084.webp","width":2000,"height":1500},"thumb":{"path":"thumbs\/DSC06084.webp","width":512,"height":410},"thumbCaption":"<span class=\"nr\">24<\/span><div class=\"title\">DSC06084<\/div>","photodata":"<b>Original Date<\/b> <i>9\/19\/22, 4:08\u202FPM<\/i> &middot; <b>Make<\/b> <i>SONY<\/i> &middot; <b>Camera<\/b> <i>DSC-HX99<\/i> &middot; <b>Lens<\/b> <i>4.25-118mm f\/3.5-6.4<\/i> &middot; <b>Focal Length (35mm)<\/b> <i>24mm<\/i> &middot; <b>Metering Mode<\/b> <i>Multi-segment<\/i> &middot; <b>ISO Equivalent<\/b> <i>100<\/i> &middot; <b>Exposure Time<\/b> <i>1\/160s<\/i> &middot; <b>Aperture<\/b> <i>ƒ\/4.5<\/i> &middot; <b>Exposure bias<\/b> <i>0 EV<\/i> &middot; <b>Exposure Program<\/b> <i>Manual control<\/i> &middot; <b>White balance<\/b> <i>Manual white balance<\/i> &middot; <b>Flash<\/b> <i>Flash did not fire<\/i> &middot; <b>Resolution<\/b> <i>4896 x 3672<\/i>","dates":{"added":1664064137,"dateTaken":1663592881},"fileDate":"2022-09-19T16:08:00.0Z","path":"DSC06084.webp","imageCaption":"<div class=\"title\">DSC06084<\/div>","fileSize":12276505,"name":"DSC06084.webp","comment":"                               ","location":"57.985725,27.623114","category":"image","camera":{"aperture":4.5,"exposureTime":"1\/160s","originalDate":"2022-09-19T16:08:01.0Z","cameraModel":"DSC-HX99","location":{"latitude":"57° 59' 8.61\"","lat":57.985725,"long":27.623114,"longitude":"27° 37' 23.21\""},"focalLength35mm":"24mm","resolution":"4896 x 3672","cameraMake":"SONY","isoEquivalent":100,"flash":"Flash did not fire","focalLength":"4mm"}},{"image":{"path":"slides\/DSC06758.webp","width":2000,"height":1500},"thumb":{"path":"thumbs\/DSC06758.webp","width":512,"height":410},"thumbCaption":"<span class=\"nr\">25<\/span><div class=\"title\">DSC06758<\/div>","photodata":"<b>Original Date<\/b> <i>9\/22\/22, 12:37\u202FPM<\/i> &middot; <b>Make<\/b> <i>SONY<\/i> &middot; <b>Camera<\/b> <i>DSC-HX99<\/i> &middot; <b>Lens<\/b> <i>4.25-118mm f\/3.5-6.4<\/i> &middot; <b>Focal Length (35mm)<\/b> <i>24mm<\/i> &middot; <b>Metering Mode<\/b> <i>Multi-segment<\/i> &middot; <b>ISO Equivalent<\/b> <i>800<\/i> &middot; <b>Exposure Time<\/b> <i>1\/80s<\/i> &middot; <b>Aperture<\/b> <i>ƒ\/3.5<\/i> &middot; <b>Exposure bias<\/b> <i>0 EV<\/i> &middot; <b>Exposure Program<\/b> <i>Manual control<\/i> &middot; <b>White balance<\/b> <i>Manual white balance<\/i> &middot; <b>Flash<\/b> <i>Flash did not fire<\/i> &middot; <b>Resolution<\/b> <i>4896 x 3672<\/i>","dates":{"added":1664064137,"dateTaken":1663839430},"fileDate":"2022-09-22T12:37:10.0Z","path":"DSC06758.webp","imageCaption":"<div class=\"title\">DSC06758<\/div>","fileSize":14861081,"name":"DSC06758.webp","comment":"                               ","location":"57.987603,27.624598","category":"image","camera":{"aperture":3.5,"exposureTime":"1\/80s","originalDate":"2022-09-22T12:37:10.0Z","cameraModel":"DSC-HX99","location":{"latitude":"57° 59' 15.37\"","lat":57.987602,"long":27.624598,"longitude":"27° 37' 28.55\""},"focalLength35mm":"24mm","resolution":"4896 x 3672","cameraMake":"SONY","isoEquivalent":800,"flash":"Flash did not fire","focalLength":"4mm"}},{"image":{"path":"slides\/DSC06759.webp","width":2000,"height":1500},"thumb":{"path":"thumbs\/DSC06759.webp","width":512,"height":410},"thumbCaption":"<span class=\"nr\">26<\/span><div class=\"title\">DSC06759<\/div>","photodata":"<b>Original Date<\/b> <i>9\/22\/22, 12:37\u202FPM<\/i> &middot; <b>Make<\/b> <i>SONY<\/i> &middot; <b>Camera<\/b> <i>DSC-HX99<\/i> &middot; <b>Lens<\/b> <i>4.25-118mm f\/3.5-6.4<\/i> &middot; <b>Focal Length (35mm)<\/b> <i>24mm<\/i> &middot; <b>Metering Mode<\/b> <i>Multi-segment<\/i> &middot; <b>ISO Equivalent<\/b> <i>800<\/i> &middot; <b>Exposure Time<\/b> <i>1\/80s<\/i> &middot; <b>Aperture<\/b> <i>ƒ\/3.5<\/i> &middot; <b>Exposure bias<\/b> <i>0 EV<\/i> &middot; <b>Exposure Program<\/b> <i>Manual control<\/i> &middot; <b>White balance<\/b> <i>Manual white balance<\/i> &middot; <b>Flash<\/b> <i>Flash did not fire<\/i> &middot; <b>Resolution<\/b> <i>4896 x 3672<\/i>","dates":{"added":1664064137,"dateTaken":1663839435},"fileDate":"2022-09-22T12:37:14.0Z","path":"DSC06759.webp","imageCaption":"<div class=\"title\">DSC06759<\/div>","fileSize":12033666,"name":"DSC06759.webp","comment":"                               ","location":"57.987598,27.624604","category":"image","camera":{"aperture":3.5,"exposureTime":"1\/80s","originalDate":"2022-09-22T12:37:15.0Z","cameraModel":"DSC-HX99","location":{"latitude":"57° 59' 15.35\"","lat":57.9876,"long":27.624603,"longitude":"27° 37' 28.57\""},"focalLength35mm":"24mm","resolution":"4896 x 3672","cameraMake":"SONY","isoEquivalent":800,"flash":"Flash did not fire","focalLength":"4mm"}},{"image":{"path":"slides\/DSC06760.webp","width":2000,"height":1500},"thumb":{"path":"thumbs\/DSC06760.webp","width":512,"height":410},"thumbCaption":"<span class=\"nr\">27<\/span><div class=\"title\">DSC06760<\/div>","photodata":"<b>Original Date<\/b> <i>9\/22\/22, 12:37\u202FPM<\/i> &middot; <b>Make<\/b> <i>SONY<\/i> &middot; <b>Camera<\/b> <i>DSC-HX99<\/i> &middot; <b>Lens<\/b> <i>4.25-118mm f\/3.5-6.4<\/i> &middot; <b>Focal Length (35mm)<\/b> <i>24mm<\/i> &middot; <b>Metering Mode<\/b> <i>Multi-segment<\/i> &middot; <b>ISO Equivalent<\/b> <i>800<\/i> &middot; <b>Exposure Time<\/b> <i>1\/80s<\/i> &middot; <b>Aperture<\/b> <i>ƒ\/3.5<\/i> &middot; <b>Exposure bias<\/b> <i>0 EV<\/i> &middot; <b>Exposure Program<\/b> <i>Manual control<\/i> &middot; <b>White balance<\/b> <i>Manual white balance<\/i> &middot; <b>Flash<\/b> <i>Flash did not fire<\/i> &middot; <b>Resolution<\/b> <i>4896 x 3672<\/i>","dates":{"added":1664064137,"dateTaken":1663839439},"fileDate":"2022-09-22T12:37:18.0Z","path":"DSC06760.webp","imageCaption":"<div class=\"title\">DSC06760<\/div>","fileSize":11293976,"name":"DSC06760.webp","comment":"                               ","location":"57.987598,27.624604","category":"image","camera":{"aperture":3.5,"exposureTime":"1\/80s","originalDate":"2022-09-22T12:37:19.0Z","cameraModel":"DSC-HX99","location":{"latitude":"57° 59' 15.35\"","lat":57.9876,"long":27.624603,"longitude":"27° 37' 28.57\""},"focalLength35mm":"24mm","resolution":"4896 x 3672","cameraMake":"SONY","isoEquivalent":800,"flash":"Flash did not fire","focalLength":"4mm"}},{"image":{"path":"slides\/DSC06761.webp","width":2000,"height":1500},"thumb":{"path":"thumbs\/DSC06761.webp","width":512,"height":410},"thumbCaption":"<span class=\"nr\">28<\/span><div class=\"title\">DSC06761<\/div>","photodata":"<b>Original Date<\/b> <i>9\/22\/22, 12:37\u202FPM<\/i> &middot; <b>Make<\/b> <i>SONY<\/i> &middot; <b>Camera<\/b> <i>DSC-HX99<\/i> &middot; <b>Lens<\/b> <i>4.25-118mm f\/3.5-6.4<\/i> &middot; <b>Focal Length (35mm)<\/b> <i>24mm<\/i> &middot; <b>Metering Mode<\/b> <i>Multi-segment<\/i> &middot; <b>ISO Equivalent<\/b> <i>800<\/i> &middot; <b>Exposure Time<\/b> <i>1\/80s<\/i> &middot; <b>Aperture<\/b> <i>ƒ\/3.5<\/i> &middot; <b>Exposure bias<\/b> <i>0 EV<\/i> &middot; <b>Exposure Program<\/b> <i>Manual control<\/i> &middot; <b>White balance<\/b> <i>Manual white balance<\/i> &middot; <b>Flash<\/b> <i>Flash did not fire<\/i> &middot; <b>Resolution<\/b> <i>4896 x 3672<\/i>","dates":{"added":1664064137,"dateTaken":1663839446},"fileDate":"2022-09-22T12:37:26.0Z","path":"DSC06761.webp","imageCaption":"<div class=\"title\">DSC06761<\/div>","fileSize":11413981,"name":"DSC06761.webp","comment":"                               ","location":"57.987575,27.624716","category":"image","camera":{"aperture":3.5,"exposureTime":"1\/80s","originalDate":"2022-09-22T12:37:26.0Z","cameraModel":"DSC-HX99","location":{"latitude":"57° 59' 15.27\"","lat":57.987576,"long":27.624716,"longitude":"27° 37' 28.98\""},"focalLength35mm":"24mm","resolution":"4896 x 3672","cameraMake":"SONY","isoEquivalent":800,"flash":"Flash did not fire","focalLength":"4mm"}},{"image":{"path":"slides\/DSC06762.webp","width":2000,"height":1500},"thumb":{"path":"thumbs\/DSC06762.webp","width":512,"height":410},"thumbCaption":"<span class=\"nr\">29<\/span><div class=\"title\">DSC06762<\/div>","photodata":"<b>Original Date<\/b> <i>9\/22\/22, 12:37\u202FPM<\/i> &middot; <b>Make<\/b> <i>SONY<\/i> &middot; <b>Camera<\/b> <i>DSC-HX99<\/i> &middot; <b>Lens<\/b> <i>4.25-118mm f\/3.5-6.4<\/i> &middot; <b>Focal Length (35mm)<\/b> <i>24mm<\/i> &middot; <b>Metering Mode<\/b> <i>Multi-segment<\/i> &middot; <b>ISO Equivalent<\/b> <i>800<\/i> &middot; <b>Exposure Time<\/b> <i>1\/80s<\/i> &middot; <b>Aperture<\/b> <i>ƒ\/3.5<\/i> &middot; <b>Exposure bias<\/b> <i>0 EV<\/i> &middot; <b>Exposure Program<\/b> <i>Manual control<\/i> &middot; <b>White balance<\/b> <i>Manual white balance<\/i> &middot; <b>Flash<\/b> <i>Flash did not fire<\/i> &middot; <b>Resolution<\/b> <i>4896 x 3672<\/i>","dates":{"added":1664064137,"dateTaken":1663839453},"fileDate":"2022-09-22T12:37:32.0Z","path":"DSC06762.webp","imageCaption":"<div class=\"title\">DSC06762<\/div>","fileSize":11560819,"name":"DSC06762.webp","comment":"                               ","location":"57.987548,27.624719","category":"image","camera":{"aperture":3.5,"exposureTime":"1\/80s","originalDate":"2022-09-22T12:37:33.0Z","cameraModel":"DSC-HX99","location":{"latitude":"57° 59' 15.17\"","lat":57.98755,"long":27.62472,"longitude":"27° 37' 28.99\""},"focalLength35mm":"24mm","resolution":"4896 x 3672","cameraMake":"SONY","isoEquivalent":800,"flash":"Flash did not fire","focalLength":"4mm"}},{"image":{"path":"slides\/DSC06763.webp","width":2000,"height":1500},"thumb":{"path":"thumbs\/DSC06763.webp","width":512,"height":410},"thumbCaption":"<span class=\"nr\">30<\/span><div class=\"title\">DSC06763<\/div>","photodata":"<b>Original Date<\/b> <i>9\/22\/22, 12:38\u202FPM<\/i> &middot; <b>Make<\/b> <i>SONY<\/i> &middot; <b>Camera<\/b> <i>DSC-HX99<\/i> &middot; <b>Lens<\/b> <i>4.25-118mm f\/3.5-6.4<\/i> &middot; <b>Focal Length (35mm)<\/b> <i>24mm<\/i> &middot; <b>Metering Mode<\/b> <i>Multi-segment<\/i> &middot; <b>ISO Equivalent<\/b> <i>800<\/i> &middot; <b>Exposure Time<\/b> <i>1\/80s<\/i> &middot; <b>Aperture<\/b> <i>ƒ\/3.5<\/i> &middot; <b>Exposure bias<\/b> <i>0 EV<\/i> &middot; <b>Exposure Program<\/b> <i>Manual control<\/i> &middot; <b>White balance<\/b> <i>Manual white balance<\/i> &middot; <b>Flash<\/b> <i>Flash did not fire<\/i> &middot; <b>Resolution<\/b> <i>4896 x 3672<\/i>","dates":{"added":1664064137,"dateTaken":1663839494},"fileDate":"2022-09-22T12:38:14.0Z","path":"DSC06763.webp","imageCaption":"<div class=\"title\">DSC06763<\/div>","fileSize":11592953,"name":"DSC06763.webp","comment":"                               ","location":"57.987578,27.624744","category":"image","camera":{"aperture":3.5,"exposureTime":"1\/80s","originalDate":"2022-09-22T12:38:14.0Z","cameraModel":"DSC-HX99","location":{"latitude":"57° 59' 15.28\"","lat":57.98758,"long":27.624744,"longitude":"27° 37' 29.08\""},"focalLength35mm":"24mm","resolution":"4896 x 3672","cameraMake":"SONY","isoEquivalent":800,"flash":"Flash did not fire","focalLength":"4mm"}},{"image":{"path":"slides\/DSC06764.webp","width":2000,"height":1500},"thumb":{"path":"thumbs\/DSC06764.webp","width":512,"height":410},"thumbCaption":"<span class=\"nr\">31<\/span><div class=\"title\">DSC06764<\/div>","photodata":"<b>Original Date<\/b> <i>9\/22\/22, 12:38\u202FPM<\/i> &middot; <b>Make<\/b> <i>SONY<\/i> &middot; <b>Camera<\/b> <i>DSC-HX99<\/i> &middot; <b>Lens<\/b> <i>4.25-118mm f\/3.5-6.4<\/i> &middot; <b>Focal Length (35mm)<\/b> <i>24mm<\/i> &middot; <b>Metering Mode<\/b> <i>Multi-segment<\/i> &middot; <b>ISO Equivalent<\/b> <i>800<\/i> &middot; <b>Exposure Time<\/b> <i>1\/80s<\/i> &middot; <b>Aperture<\/b> <i>ƒ\/3.5<\/i> &middot; <b>Exposure bias<\/b> <i>0 EV<\/i> &middot; <b>Exposure Program<\/b> <i>Manual control<\/i> &middot; <b>White balance<\/b> <i>Manual white balance<\/i> &middot; <b>Flash<\/b> <i>Flash did not fire<\/i> &middot; <b>Resolution<\/b> <i>4896 x 3672<\/i>","dates":{"added":1664064137,"dateTaken":1663839504},"fileDate":"2022-09-22T12:38:24.0Z","path":"DSC06764.webp","imageCaption":"<div class=\"title\">DSC06764<\/div>","fileSize":11959013,"name":"DSC06764.webp","comment":"                               ","location":"57.987583,27.624705","category":"image","camera":{"aperture":3.5,"exposureTime":"1\/80s","originalDate":"2022-09-22T12:38:24.0Z","cameraModel":"DSC-HX99","location":{"latitude":"57° 59' 15.3\"","lat":57.987583,"long":27.624704,"longitude":"27° 37' 28.94\""},"focalLength35mm":"24mm","resolution":"4896 x 3672","cameraMake":"SONY","isoEquivalent":800,"flash":"Flash did not fire","focalLength":"4mm"}},{"image":{"path":"slides\/DSC06765.webp","width":2000,"height":1500},"thumb":{"path":"thumbs\/DSC06765.webp","width":512,"height":410},"thumbCaption":"<span class=\"nr\">32<\/span><div class=\"title\">DSC06765<\/div>","photodata":"<b>Original Date<\/b> <i>9\/22\/22, 12:38\u202FPM<\/i> &middot; <b>Make<\/b> <i>SONY<\/i> &middot; <b>Camera<\/b> <i>DSC-HX99<\/i> &middot; <b>Lens<\/b> <i>4.25-118mm f\/3.5-6.4<\/i> &middot; <b>Focal Length (35mm)<\/b> <i>24mm<\/i> &middot; <b>Metering Mode<\/b> <i>Multi-segment<\/i> &middot; <b>ISO Equivalent<\/b> <i>800<\/i> &middot; <b>Exposure Time<\/b> <i>1\/80s<\/i> &middot; <b>Aperture<\/b> <i>ƒ\/3.5<\/i> &middot; <b>Exposure bias<\/b> <i>0 EV<\/i> &middot; <b>Exposure Program<\/b> <i>Manual control<\/i> &middot; <b>White balance<\/b> <i>Manual white balance<\/i> &middot; <b>Flash<\/b> <i>Flash did not fire<\/i> &middot; <b>Resolution<\/b> <i>4896 x 3672<\/i>","dates":{"added":1664064137,"dateTaken":1663839505},"fileDate":"2022-09-22T12:38:24.0Z","path":"DSC06765.webp","imageCaption":"<div class=\"title\">DSC06765<\/div>","fileSize":11979926,"name":"DSC06765.webp","comment":"                               ","location":"57.987583,27.624705","category":"image","camera":{"aperture":3.5,"exposureTime":"1\/80s","originalDate":"2022-09-22T12:38:25.0Z","cameraModel":"DSC-HX99","location":{"latitude":"57° 59' 15.3\"","lat":57.987583,"long":27.624704,"longitude":"27° 37' 28.94\""},"focalLength35mm":"24mm","resolution":"4896 x 3672","cameraMake":"SONY","isoEquivalent":800,"flash":"Flash did not fire","focalLength":"4mm"}},{"image":{"path":"slides\/DSC06840.webp","width":2000,"height":1500},"thumb":{"path":"thumbs\/DSC06840.webp","width":512,"height":410},"thumbCaption":"<span class=\"nr\">33<\/span><div class=\"title\">DSC06840<\/div>","photodata":"<b>Original Date<\/b> <i>10\/2\/21, 2:33\u202FPM<\/i> &middot; <b>Make<\/b> <i>SONY<\/i> &middot; <b>Camera<\/b> <i>DSC-HX90V<\/i> &middot; <b>Lens<\/b> <i>4.1-123mm f\/3.5-6.4<\/i> &middot; <b>Focal Length (35mm)<\/b> <i>24mm<\/i> &middot; <b>Metering Mode<\/b> <i>Multi-segment<\/i> &middot; <b>ISO Equivalent<\/b> <i>200<\/i> &middot; <b>Exposure Time<\/b> <i>1\/125s<\/i> &middot; <b>Aperture<\/b> <i>ƒ\/4<\/i> &middot; <b>Exposure bias<\/b> <i>0 EV<\/i> &middot; <b>Exposure Program<\/b> <i>Manual control<\/i> &middot; <b>White balance<\/b> <i>Manual white balance<\/i> &middot; <b>Flash<\/b> <i>Flash did not fire<\/i> &middot; <b>Resolution<\/b> <i>4896 x 3672<\/i>","dates":{"added":1633205755,"dateTaken":1633174438},"fileDate":"2021-10-02T14:33:58.0Z","path":"DSC06840.webp","imageCaption":"<div class=\"title\">DSC06840<\/div>","fileSize":7423172,"name":"DSC06840.webp","comment":"                               ","location":"59.462506,25.756693","category":"image","camera":{"aperture":4.0,"exposureTime":"1\/125s","originalDate":"2021-10-02T14:33:58.0Z","cameraModel":"DSC-HX90V","location":{"altitude":"56.8 metres","latitude":"59° 27' 45.02\"","lat":59.462505,"long":25.756693,"longitude":"25° 45' 24.09\""},"focalLength35mm":"24mm","resolution":"4896 x 3672","cameraMake":"SONY","isoEquivalent":200,"flash":"Flash did not fire","focalLength":"4mm"}},{"image":{"path":"slides\/DSC06841.webp","width":2000,"height":1500},"thumb":{"path":"thumbs\/DSC06841.webp","width":512,"height":410},"thumbCaption":"<span class=\"nr\">34<\/span><div class=\"title\">DSC06841<\/div>","photodata":"<b>Original Date<\/b> <i>10\/2\/21, 2:34\u202FPM<\/i> &middot; <b>Make<\/b> <i>SONY<\/i> &middot; <b>Camera<\/b> <i>DSC-HX90V<\/i> &middot; <b>Lens<\/b> <i>4.1-123mm f\/3.5-6.4<\/i> &middot; <b>Focal Length (35mm)<\/b> <i>24mm<\/i> &middot; <b>Metering Mode<\/b> <i>Multi-segment<\/i> &middot; <b>ISO Equivalent<\/b> <i>200<\/i> &middot; <b>Exposure Time<\/b> <i>1\/125s<\/i> &middot; <b>Aperture<\/b> <i>ƒ\/4<\/i> &middot; <b>Exposure bias<\/b> <i>0 EV<\/i> &middot; <b>Exposure Program<\/b> <i>Manual control<\/i> &middot; <b>White balance<\/b> <i>Manual white balance<\/i> &middot; <b>Flash<\/b> <i>Flash did not fire<\/i> &middot; <b>Resolution<\/b> <i>4896 x 3672<\/i>","dates":{"added":1633205755,"dateTaken":1633174445},"fileDate":"2021-10-02T14:34:04.0Z","path":"DSC06841.webp","imageCaption":"<div class=\"title\">DSC06841<\/div>","fileSize":6194319,"name":"DSC06841.webp","comment":"                               ","location":"59.462501,25.756705","category":"image","camera":{"aperture":4.0,"exposureTime":"1\/125s","originalDate":"2021-10-02T14:34:05.0Z","cameraModel":"DSC-HX90V","location":{"altitude":"57.4 metres","latitude":"59° 27' 45\"","lat":59.4625,"long":25.756704,"longitude":"25° 45' 24.14\""},"focalLength35mm":"24mm","resolution":"4896 x 3672","cameraMake":"SONY","isoEquivalent":200,"flash":"Flash did not fire","focalLength":"4mm"}},{"image":{"path":"slides\/DSC06842.webp","width":2000,"height":1500},"thumb":{"path":"thumbs\/DSC06842.webp","width":512,"height":410},"thumbCaption":"<span class=\"nr\">35<\/span><div class=\"title\">DSC06842<\/div>","photodata":"<b>Original Date<\/b> <i>10\/2\/21, 2:35\u202FPM<\/i> &middot; <b>Make<\/b> <i>SONY<\/i> &middot; <b>Camera<\/b> <i>DSC-HX90V<\/i> &middot; <b>Lens<\/b> <i>4.1-123mm f\/3.5-6.4<\/i> &middot; <b>Focal Length (35mm)<\/b> <i>24mm<\/i> &middot; <b>Metering Mode<\/b> <i>Multi-segment<\/i> &middot; <b>ISO Equivalent<\/b> <i>200<\/i> &middot; <b>Exposure Time<\/b> <i>1\/125s<\/i> &middot; <b>Aperture<\/b> <i>ƒ\/4<\/i> &middot; <b>Exposure bias<\/b> <i>0 EV<\/i> &middot; <b>Exposure Program<\/b> <i>Manual control<\/i> &middot; <b>White balance<\/b> <i>Manual white balance<\/i> &middot; <b>Flash<\/b> <i>Flash did not fire<\/i> &middot; <b>Resolution<\/b> <i>4896 x 3672<\/i>","dates":{"added":1633205755,"dateTaken":1633174516},"fileDate":"2021-10-02T14:35:16.0Z","path":"DSC06842.webp","imageCaption":"<div class=\"title\">DSC06842<\/div>","fileSize":6625300,"name":"DSC06842.webp","comment":"                               ","location":"59.462476,25.756710","category":"image","camera":{"aperture":4.0,"exposureTime":"1\/125s","originalDate":"2021-10-02T14:35:16.0Z","cameraModel":"DSC-HX90V","location":{"altitude":"57.5 metres","latitude":"59° 27' 44.92\"","lat":59.462475,"long":25.75671,"longitude":"25° 45' 24.16\""},"focalLength35mm":"24mm","resolution":"4896 x 3672","cameraMake":"SONY","isoEquivalent":200,"flash":"Flash did not fire","focalLength":"4mm"}},{"image":{"path":"slides\/DSC06843.webp","width":2000,"height":1500},"thumb":{"path":"thumbs\/DSC06843.webp","width":512,"height":410},"thumbCaption":"<span class=\"nr\">36<\/span><div class=\"title\">DSC06843<\/div>","photodata":"<b>Original Date<\/b> <i>10\/2\/21, 2:35\u202FPM<\/i> &middot; <b>Make<\/b> <i>SONY<\/i> &middot; <b>Camera<\/b> <i>DSC-HX90V<\/i> &middot; <b>Lens<\/b> <i>4.1-123mm f\/3.5-6.4<\/i> &middot; <b>Focal Length (35mm)<\/b> <i>24mm<\/i> &middot; <b>Metering Mode<\/b> <i>Multi-segment<\/i> &middot; <b>ISO Equivalent<\/b> <i>200<\/i> &middot; <b>Exposure Time<\/b> <i>1\/125s<\/i> &middot; <b>Aperture<\/b> <i>ƒ\/4<\/i> &middot; <b>Exposure bias<\/b> <i>0 EV<\/i> &middot; <b>Exposure Program<\/b> <i>Manual control<\/i> &middot; <b>White balance<\/b> <i>Manual white balance<\/i> &middot; <b>Flash<\/b> <i>Flash did not fire<\/i> &middot; <b>Resolution<\/b> <i>4896 x 3672<\/i>","dates":{"added":1633205755,"dateTaken":1633174519},"fileDate":"2021-10-02T14:35:18.0Z","path":"DSC06843.webp","imageCaption":"<div class=\"title\">DSC06843<\/div>","fileSize":6474265,"name":"DSC06843.webp","comment":"                               ","location":"59.462486,25.756708","category":"image","camera":{"aperture":4.0,"exposureTime":"1\/125s","originalDate":"2021-10-02T14:35:19.0Z","cameraModel":"DSC-HX90V","location":{"altitude":"57.6 metres","latitude":"59° 27' 44.95\"","lat":59.462486,"long":25.756708,"longitude":"25° 45' 24.15\""},"focalLength35mm":"24mm","resolution":"4896 x 3672","cameraMake":"SONY","isoEquivalent":200,"flash":"Flash did not fire","focalLength":"4mm"}}],"name":"Говорушка благоухающая - Clitocybe fragrans","dates":{"added":1664064137,"dateRange":{"0":1599649398,"1":1663839505}},"fileDate":"2023-02-04T01:50:48.906Z"}